[
  {
    "Moniteur": "Carlos",
    "Date": "2025-10-28",
    "Eleve": "",
    "Role": "DP",
    "CR": ""
  },
  {
    "Moniteur": "Christophe",
    "Date": "2025-11-18",
    "Eleve": "",
    "Role": "DP",
    "CR": ""
  },
  {
    "Moniteur": "Eddy",
    "Date": "2025-11-25",
    "Eleve": "",
    "Role": "DP",
    "CR": ""
  },
  {
    "Moniteur": "Eddy",
    "Date": "2025-12-02",
    "Eleve": "",
    "Role": "DP",
    "CR": ""
  },
  {
    "Moniteur": "Eddy",
    "Date": "2025-12-09",
    "Eleve": "",
    "Role": "DP",
    "CR": ""
  },
  {
    "Moniteur": "Eddy",
    "Date": "2026-01-13",
    "Eleve": "",
    "Role": "DP",
    "CR": ""
  },
  {
    "Moniteur": "Carlos",
    "Date": "2026-01-27",
    "Eleve": "",
    "Role": "DP",
    "CR": ""
  },
  {
    "Moniteur": "Benoit L.",
    "Date": "2026-02-03",
    "Eleve": "",
    "Role": "DP",
    "CR": ""
  },
  {
    "Moniteur": "Eddy",
    "Date": "2026-02-10",
    "Eleve": "",
    "Role": "DP",
    "CR": ""
  },
  {
    "Moniteur": "Benoit P.",
    "Date": "2026-02-24",
    "Eleve": "",
    "Role": "DP",
    "CR": ""
  },
  {
    "Moniteur": "Virginie",
    "Date": "2026-03-03",
    "Eleve": "",
    "Role": "DP",
    "CR": ""
  },
  {
    "Moniteur": "Carine",
    "Date": "2026-03-17",
    "Eleve": "",
    "Role": "DP",
    "CR": ""
  },
  {
    "Moniteur": "Eddy",
    "Date": "2026-03-24",
    "Eleve": "",
    "Role": "DP",
    "CR": ""
  },
  {
    "Moniteur": "Carlos",
    "Date": "2026-04-14",
    "Eleve": "",
    "Role": "DP",
    "CR": ""
  },
  {
    "Moniteur": "Virginie",
    "Date": "2026-04-21",
    "Eleve": "",
    "Role": "DP",
    "CR": ""
  },
  {
    "Moniteur": "Benoit L.",
    "Date": "2025-09-30",
    "Eleve": "JUDICAËL",
    "Role": "Encadrant",
    "CR": "Baptême réalisé sans CACI, avec respect des consignes de sécurité. Le gréage et le décapelage ont été présentés : le mémo 0213 est bien assimilé et la sangle correctement fixée dès le premier essai, mais la connaissance des éléments de la stab reste à renforcer. Communication sous-marine maîtrisée (OK, monter, descendre), et l’exercice du poumon-ballast est compris. Palmage en immersion non acquis (mouvement type vélo), et l’aisance aquatique reste limitée, avec sensation de froid en fin de plongée. Comportement calme, réactif aux consignes, sans stress respiratoire ; bonne capacité à continuer malgré un peu d’eau dans le masque, ce qui est encourageant pour la suite."
  },
  {
    "Moniteur": "Benoit P.",
    "Date": "2025-09-30",
    "Eleve": "TIMEO",
    "Role": "Encadrant",
    "CR": "Baptême réalisé sans CACI, avec respect des consignes et bonne aisance aquatique. Le gréage et le dégréage sont bien exécutés, même si la connaissance des éléments de la stab reste à renforcer ; capelage/décapelage maîtrisés. Communication sous-marine acquise (OK, monter, descendre, froid, fin de plongée) et palmage en immersion correct. Première utilisation de la purge lente au fond pour illustrer la position du Direct System, et compréhension du signal de fin de plongée. Comportement calme, attentif et sportif, malgré un peu de froid en fin de séance ; débriefing non réalisé après le décapelage."
  },
  {
    "Moniteur": "Véronique",
    "Date": "2025-09-30",
    "Eleve": "FLORENT",
    "Role": "Encadrant",
    "CR": "Florent est très à l’écoute et maîtrise bien le gréage, capelage et décapelage, avec une bonne compréhension des fonctions des différents éléments. Contrôle du matériel avant la descente effectué correctement. La descente s’est bien déroulée, même si l’assistance a été nécessaire pour le dégonflage ; au fond, il est resté posé et stable, avec des déplacements fluides et une bonne aisance aquatique. La remontée a été réalisée seul à vitesse correcte, avec un bon contrôle respiratoire. Son expérience en chasse sous-marine lui donne déjà quelques repères utiles pour la suite."
  },
  {
    "Moniteur": "Carlos",
    "Date": "2025-09-30",
    "Eleve": "JEREMIE",
    "Role": "Encadrant",
    "CR": "J'ai plongé avec Jeremy, il avait pas mal de connaissances sur la plongée.   Il avait fait plusieurs baptêmes en mer. Masque toujours plein, il était alaise pendant les balades sous l'eau... il a géré un peu le direct système, il répond bien au signe okey. Deviendra très certainement un bon N1 après notre formation."
  },
  {
    "Moniteur": "Eddy",
    "Date": "2025-09-30",
    "Eleve": "MELINE",
    "Role": "Encadrant",
    "CR": "Très à l’aise et aquatique dès la première séance.\nGréage et dégréage en cours d’acquisition, avec bonne écoute et restitution des gestes.\nCapelage en surface : RAS.\nDeux descentes lentes mais bien réalisées, sans remontée lors des déplacements.\nExcellente attitude pour une première séance, prometteuse pour la suite."
  },
  {
    "Moniteur": "Eddy",
    "Date": "2025-09-30",
    "Eleve": "STEPHANE",
    "Role": "Encadrant",
    "CR": "- gréage et dégréage : en cours d'acquisition avec une bonne écoute et une bonne restitution des gestes. Il vont rapidement assimiler cela\n- Capelage en surface : ras\n- 2 descentes très lentes en dégonflant leur gilet : bien dans l'ensemble\nStéphane avait un shorty et donc il avait tendance à remonter. Il fallait régulièrement le tenir. De plus, il ne souffle pas assez mais c'est normal à ce stade de la formation ! Il m'a dit qu'il enlèverait son shorty la prochaine fois.\nMéline est très à l'aise, aquatique. Pas de remontée lorsqu'elle se déplace. C'était top pour une première."
  },
  {
    "Moniteur": "Virginie",
    "Date": "2025-09-30",
    "Eleve": "SACHA",
    "Role": "Encadrant",
    "CR": "Très à l’aise et aquatique dès la première séance.\nGréage et dégréage en cours d’acquisition, avec bonne écoute et restitution des gestes.\nCapelage en surface : RAS.\nDeux descentes lentes mais bien réalisées, sans remontée lors des déplacements.\nExcellente attitude pour une première séance"
  },
  {
    "Moniteur": "Christophe",
    "Date": "2025-09-30",
    "Eleve": "SAMY",
    "Role": "Encadrant",
    "CR": "Très à l’aise et aquatique dès la première séance.\nGréage et dégréage en cours d’acquisition, avec bonne écoute et restitution des gestes.\nCapelage en surface : RAS.\nDeux descentes lentes mais bien réalisées, sans remontée lors des déplacements.\nExcellente attitude pour une première séance"
  },
  {
    "Moniteur": "Carine",
    "Date": "2025-09-30",
    "Eleve": "GAËLLE",
    "Role": "Encadrant",
    "CR": "Gaëlle est attentive lors du gréage et dégréage et reproduit correctement les gestes.\nL’immersion a été stressante au départ, avec une assistance nécessaire, puis le stress a diminué au fond.\nEn exploration, elle a tendance à remonter mais reste réceptive aux consignes et répond au signe OK.\nPlongée prometteuse, élève motivée, avec un stress accentué par des accidents de plongée passés dans son entourage."
  },
  {
    "Moniteur": "Eddy",
    "Date": "2025-10-07",
    "Eleve": "TIMEO",
    "Role": "Encadrant",
    "CR": "Gréage et dégréage corrects, vocabulaire en cours d’acquisition.\nSignes de communication maîtrisés, notamment pour la pression et les cas particuliers (100 et 50 bar).\nDescente avec purge lente difficile au début (ne souffle pas assez), mais amélioration après explications et retrait du shorty ; le déclic est venu et elle a pu rester au fond.\nBalade finale en autonomie sans aide, avec une bonne remontée lente et gestion du matériel après plongée : OK.\nStress initial classique, corrigé par travail sur la respiration plutôt que par ajout de plombs"
  },
  {
    "Moniteur": "Benoit L.",
    "Date": "2025-10-07",
    "Eleve": "FLORENT",
    "Role": "Encadrant",
    "CR": "Florent a montré une bonne maîtrise des bases techniques : gréage/dégréage, capelage/décapelage et communication sous-marine, avec assimilation des signes essentiels. Le palmage en surface et en immersion est correctement exécuté, sans problème notable, et la gestion de la flottabilité (descente, purge lente, position au fond) est satisfaisante. L’atelier consommation est acquis : Florent sait consulter son manomètre, annoncer la pression et signaler la mi-pression spontanément. L’exercice du poumon-ballast est bien compris et réalisé avec précision. Comportement calme et concentré, progression régulière et attitude favorable à la poursuite de la formation."
  },
  {
    "Moniteur": "Catherine",
    "Date": "2025-10-07",
    "Eleve": "SACHA",
    "Role": "Encadrant",
    "CR": "Sacha était enrhumé avec le nez bouché, ce qui a limité la séance. Le gréage est en cours d’acquisition et l’équipement dans l’eau a été travaillé. Il a tenté la descente mais n’a pas pu poursuivre en raison de douleurs importantes aux oreilles. Malgré ces difficultés, il a montré de la volonté et reste engagé dans son apprentissage."
  },
  {
    "Moniteur": "Véronique",
    "Date": "2025-10-07",
    "Eleve": "STEPHANE",
    "Role": "Encadrant",
    "CR": "Stéphane maîtrise le gréage/dégréage, le capelage/décapelage et le vocabulaire technique, en commentant correctement ses actions.\nLa descente est globalement acquise malgré un démarrage difficile, avec encore des difficultés de stabilisation au fond et entre deux eaux liées au contrôle de la respiration.\nLe travail poumon-ballast a permis de retrouver le calme et de mieux comprendre le rôle du souffle ; la remontée lente est bien gérée avec une assistance minimale.\nPlongeur motivé et attentif à ses sensations, encore un peu tendu, très investi théoriquement, avec des projets de plongées et de formation à court terme."
  },
  {
    "Moniteur": "Benoit P.",
    "Date": "2025-10-07",
    "Eleve": "SAMY",
    "Role": "Encadrant",
    "CR": "Sami maîtrise le gréage, la mise à l’eau, le capelage et la communication, avec une bonne connaissance de son matériel et des signes usuels.\nLa descente, le palmage et la purge lente sont bien réalisés, mais l’utilisation des poumons-ballast reste à consolider, notamment lors des phases d’expiration.\nLa remontée contrôlée est acquise, avec une bonne compréhension de la lenteur et une gestion autonome du gonflage en surface.\nSéance globalement positive malgré des contraintes matérielles et d’espace, avec un débriefing approfondi rendu possible par une sortie d’eau anticipée."
  },
  {
    "Moniteur": "Christophe",
    "Date": "2025-10-07",
    "Eleve": "ROBIN",
    "Role": "Encadrant",
    "CR": "Robin réalise sa première séance de plongée avec une compréhension globale du matériel, du gréage et des règles de sécurité.\nLors de la séance, il se déconcentre facilement mais reste réactif aux consignes et répond correctement aux signes.\nLa descente avec purge lente, les exercices de poumon-ballast et la remontée lente sont acquis, malgré une vigilance nécessaire sur l’équilibrage des oreilles et le palmage.\nSéance positive pour une première plongée, avec des bases solides à consolider en stabilité et en technique de palmage."
  },
  {
    "Moniteur": "Carine",
    "Date": "2025-10-07",
    "Eleve": "JEREMIE",
    "Role": "Encadrant",
    "CR": "Jérémy maîtrise le gréage et la vérification du matériel en totale autonomie.\nLa descente est bien gérée avec la purge, malgré une légère difficulté à se stabiliser au fond liée à de l’air résiduel dans la stab.\nEn immersion, le palmage est à travailler, mais la compréhension du poumon-ballast et l’utilisation des signes sont acquises.\nTrès bonne gestion du masque malgré des entrées d’eau répétées, avec des vidages réalisés seul, masque à changer car inadapté à son visage."
  },
  {
    "Moniteur": "Guillaume",
    "Date": "2025-10-07",
    "Eleve": "MELINE",
    "Role": "Encadrant",
    "CR": "Méline avait des oublis sur le gréage du bloc, point qui a été entièrement revu et sera à réévaluer lors de la prochaine séance.\nEn immersion, elle est très à l’aise : descente à la purge lente maîtrisée dès le premier essai, avec une vitesse parfaitement contrôlée.\nLes exercices de poumon-ballast sont acquis et elle présente une très bonne stabilisation, sans mouvements parasites.\nLa communication, notamment sur la pression, est correctement comprise et utilisée."
  },
  {
    "Moniteur": "Charles",
    "Date": "2025-10-07",
    "Eleve": "TIMEO",
    "Role": "Encadrant",
    "CR": "Timéo a réalisé un baptême ++ dans de très bonnes conditions, avec une découverte complète du gréage et du dégréage du matériel.\nLa mise à l’eau, l’équipement en surface et les signes de base sont bien compris et correctement appliqués.\nEn immersion, il se montre à l’aise, sans stress, posé au fond et mobile dans la cage avec aisance.\nComportement calme et concentré, nécessitant toutefois une proximité renforcée du fait de la forte affluence de plongeurs au fond."
  },
  {
    "Moniteur": "Carine",
    "Date": "2025-10-14",
    "Eleve": "LUDOVIC",
    "Role": "Encadrant",
    "CR": "Ludovic a réalisé un baptême ++ en l’absence de CACI, situation qui sera identique la semaine prochaine en attente de son rendez-vous médical.\nLes bases de gréage, dégréage et la communication du manomètre lui ont été présentées.\nIl répond correctement aux signes et gère bien son matériel."
  },
  {
    "Moniteur": "Christophe",
    "Date": "2025-10-14",
    "Eleve": "NALINI",
    "Role": "Encadrant",
    "CR": "Nalini a réalisé un baptême ++ en l’absence de CACI, avec une présentation complète du matériel et des règles de sécurité de base.\nLe gréage reste à perfectionner, mais la mise à l’eau, la descente lente et l’évolution stabilisée sont bien maîtrisées.\nPlongeuse aquatique, calme, avec un bon palmage, une posture adaptée et une bonne compréhension du poumon-ballast et de la communication.\nUn épisode de vertige alterno-barique est survenu en remontée, résolu rapidement en surface, avec vigilance à prévoir sur la manipulation d’un bloc lourd pour elle."
  },
  {
    "Moniteur": "Charles",
    "Date": "2025-10-14",
    "Eleve": "GAËLLE",
    "Role": "Encadrant",
    "CR": "Gaëlle a montré une très bonne attitude, attentive et motivée. Les exercices de gréage, dégréage, capelage, décapelage, communication et déplacements ont été réalisés correctement. Elle progresse bien sur le poumon ballast malgré quelques incidents gérés sans panique. La descente reste difficile même avec purge lente et gilet vidé, et elle a eu des soucis d’eau dans le masque, avec une légère panique initiale. À travailler : gestion du masque et respiration par le nez (DBN)."
  },
  {
    "Moniteur": "Eddy",
    "Date": "2025-10-14",
    "Eleve": "TIMEO",
    "Role": "Encadrant",
    "CR": "Première séance après obtention du CACI, profil similaire à Florent : très à l’aise et attentif.\nGréage/dégréage, capelage et décapelage réalisés sans difficulté.\nCommunication excellente, maîtrise des signes dont celui du froid.\nDescente à la purge lente parfaitement exécutée, bonne utilisation du poumon ballast sur plusieurs exercices.\nSur la deuxième REC, il a géré son gilet en autonomie sans problème : RAS"
  },
  {
    "Moniteur": "Benoit L.",
    "Date": "2025-10-14",
    "Eleve": "SAMY",
    "Role": "Encadrant",
    "CR": "Gréage et dégréage bien exécutés, même si le vocabulaire reste en cours d’acquisition ; maîtrise correcte des gestes techniques (boucle 0-213, fixation, ouverture/fermeture du robinet, purge).\nCommunication sous-marine maîtrisée : signes OK, problème, montée, descente, froid (avec niveaux), fin d’exercice ; bonne compréhension des signes liés à la consommation (mi-pression, 50 bars).\nDescente avec purge lente réalisée correctement, position à genoux respectée ; bonne gestion du Direct System.\nExercice poumon-ballast acquis, avec progression vers un déplacement dynamique en « pas à pas » très bien réalisé.\nComportement calme et concentré, aucune manifestation de stress ; progression régulière sur la technique, revoir le palmage et continuer la révision des termes du matériel."
  },
  {
    "Moniteur": "Benoit P.",
    "Date": "2025-10-14",
    "Eleve": "FLORENT",
    "Role": "Encadrant",
    "CR": "Franchement pas grand chose a dire....\nFlo gère très bien: \n● Le gréage/dégréage\n● Capelage et décapelage \n● La communication, Il m'a fait signe mi pression de lui même. \n● La descente avec la purge lente\n● Le poumon ballast : Nous avons fait des \"pompes\", puis exercice assis, puis stabilisation lotus, puis stabilisation surface avec juste la main en surface\n● La REC avec les palmes et sans utiliser les palmes le tout a vitesse très lente."
  },
  {
    "Moniteur": "Catherine",
    "Date": "2025-10-21",
    "Eleve": "LUDOVIC",
    "Role": "Encadrant",
    "CR": "Baptême + avec Ludovic en l'absence de CACI. Gréage a  refaire mais beaucoup d’aisance dans l’eau."
  },
  {
    "Moniteur": "Benoit P.",
    "Date": "2025-10-21",
    "Eleve": "NALINI",
    "Role": "Encadrant",
    "CR": "Globalement, la natation s’est bien déroulée pour tous, même si Judicaël pédale encore un peu. En fosse, Nalini a réalisé son baptême avec aisance malgré l’absence de CACI (en attente de validation par un médecin du sport). Le gréage était hésitant mais validé, capelage, décapelage et dégréage corrects, lecture du mano OK. Pas d’instruction subaquatique, mais la balade sous l’eau s’est faite avec confort. Nalini est attentive et assimile bien les conseils."
  },
  {
    "Moniteur": "Eddy",
    "Date": "2025-10-21",
    "Eleve": "SACHA",
    "Role": "Encadrant",
    "CR": "Avec Sacha et Judicaël, la boucle 0213 a été complètement oubliée et le gréage reste très hésitant, tout comme le vocabulaire. Capelage en surface OK pour les deux, et la descente à la purge lente bien maîtrisée. Sacha a dû arrêter la plongée à cause d’un problème d’oreille lié à un rhume persistant. Judicaël est très zen sous l’eau, communique bien, a géré le PB, la balade et la REC, avec un bon comportement général. Décapelage et dégréage OK, et il a reçu des conseils pour le séchage du matériel."
  },
  {
    "Moniteur": "Eddy",
    "Date": "2025-10-21",
    "Eleve": "JUDICAËL",
    "Role": "Encadrant",
    "CR": "Avec Sacha et Judicaël, la boucle 0213 a été oubliée et le gréage reste très hésitant, tout comme le vocabulaire. Capelage en surface OK pour les deux, et la descente à la purge lente bien maîtrisée. Sacha a dû arrêter la plongée à cause d’un problème d’oreille lié à un rhume persistant. Judicaël est très zen sous l’eau, communique bien, a géré le PB, la balade et la REC, avec une progression régulière. Décapelage et dégréage OK, et il a reçu des conseils pour le séchage du matériel."
  },
  {
    "Moniteur": "Benoit L.",
    "Date": "2025-10-21",
    "Eleve": "JEREMIE",
    "Role": "Encadrant",
    "CR": "Jérémie a montré une bonne écoute et une attitude concentrée tout au long de l’atelier. Les bases techniques sont solides : gréage/dégréage, capelage/décapelage, communication et palmage sont globalement maîtrisés, malgré quelques confusions droite/gauche à corriger. Il a bien intégré les notions de purge lente, poumon-ballast et remontée au DS, avec des exercices réalisés sans précipitation. La gestion de la consommation est acquise, ainsi que les signes associés. Son comportement est calme et sérieux, ce qui favorise une progression régulière et la poursuite de la formation technique."
  },
  {
    "Moniteur": "Carine",
    "Date": "2025-10-21",
    "Eleve": "TIMEO",
    "Role": "Encadrant",
    "CR": "Avec Timeo et Samy, tout s’est déroulé parfaitement, aucune difficulté à signaler. Ils ont bien géré la surveillance de leur manomètre et ont signalé la réserve comme demandé (60b puis 50b avec le signe approprié). Attitude sérieuse et respect des consignes."
  },
  {
    "Moniteur": "Carine",
    "Date": "2025-10-21",
    "Eleve": "SAMY",
    "Role": "Encadrant",
    "CR": "Avec Timeo et Samy, la plongée s’est déroulée sans problème, tout était parfaitement maîtrisé. Ils ont bien respecté la consigne sur la surveillance du manomètre et ont signalé la réserve comme demandé (60b puis 50b avec le signe approprié). Attitude sérieuse et conforme aux attentes."
  },
  {
    "Moniteur": "Christophe",
    "Date": "2025-10-28",
    "Eleve": "SAMY",
    "Role": "Encadrant",
    "CR": "Avec Samy, la séance s’est bien déroulée et il était motivé. Le gréage reste à perfectionner, notamment sur la hauteur de fixation du gilet. Les exercices de respiration sans masque et DBN ont été réussis dès la première tentative et répétés avec succès. Descente à la purge lente, signes, stabilisation à 3 m et utilisation du poumon ballast corrects, malgré une légère tendance à remonter en fin de trajet. Vidage partiel du masque, REC et remontée maîtrisés ; Samy était heureux et satisfait de la séance."
  },
  {
    "Moniteur": "Benoit L.",
    "Date": "2025-10-28",
    "Eleve": "SACHA",
    "Role": "Encadrant",
    "CR": "Avec Sacha et Florent, l’atelier technique s’est bien déroulé. Florent montre une bonne maîtrise des signes et de la dénomination du matériel, tandis que Sacha doit encore revoir ces notions ainsi que le signe du froid. Les deux ont correctement réalisé gréage, dégréage, capelage et exercices de communication, consommation, poumon-ballast et remontée au DS, avec une progression régulière. Florent est calme et stable en immersion, sensible au froid en fin de séance ; Sacha est attentif mais doit travailler la stabilité et limiter l’usage des mains. Globalement, bases solides pour Florent et progression encourageante pour Sacha, avec recommandations ciblées pour la suite."
  },
  {
    "Moniteur": "Benoit L.",
    "Date": "2025-10-28",
    "Eleve": "FLORENT",
    "Role": "Encadrant",
    "CR": "Avec Sacha et Florent, l’atelier technique s’est bien déroulé. Florent montre une bonne maîtrise des signes et de la dénomination du matériel, tandis que Sacha doit encore revoir ces notions ainsi que le signe du froid. Les deux ont correctement réalisé gréage, dégréage, capelage et exercices de communication, consommation, poumon-ballast et remontée au DS, avec une progression régulière. Florent est calme et stable en immersion, sensible au froid en fin de séance ; Sacha est attentif mais doit travailler la stabilité et limiter l’usage des mains. Globalement, bases solides pour Florent et progression encourageante pour Sacha, avec recommandations ciblées pour la suite."
  },
  {
    "Moniteur": "Benoit P.",
    "Date": "2025-10-28",
    "Eleve": "JUDICAËL",
    "Role": "Encadrant",
    "CR": "Avec Judicaël, le gréage est en cours d’apprentissage, tandis que le capelage, la descente et le dégréage sont acquis. Il a bien compris le principe du poumon ballast et progresse sur la RSE, encore en cours d’acquisition. La lecture du manomètre est correcte sur demande, mais la communication reste partiellement maîtrisée. Le palmage, en surface comme en immersion, nécessite un travail supplémentaire. Globalement, Jude assimile les conseils à son rythme et corrige ses erreurs avec sérieux."
  },
  {
    "Moniteur": "Véronique",
    "Date": "2025-10-28",
    "Eleve": "TIMEO",
    "Role": "Encadrant",
    "CR": "Avec Matéo et Jérémie, le gréage, dégréage et capelage en surface sont acquis, avec un bon réflexe de Matéo qui a détecté des bulles et procédé au changement de bloc. La descente à la purge lente est bien réalisée par Matéo, plus difficile pour Jérémie qui peine à rester au fond malgré ses efforts pour souffler. Les exercices de poumon ballast et REC sont réussis, mais Jérémie reste gêné par une stab trop petite et compense en palmant, ce qui affecte sa stabilisation. Les signes et la lecture du manomètre sont maîtrisés, et la gestion du matériel en fin de plongée est correcte. Jérémie progresse mais devra tester une stab adaptée et peut-être un léger lestage pour améliorer son confort et sa stabilité."
  },
  {
    "Moniteur": "Véronique",
    "Date": "2025-10-28",
    "Eleve": "JEREMIE",
    "Role": "Encadrant",
    "CR": "Avec Matéo et Jérémie, le gréage, dégréage et capelage en surface sont acquis, avec un bon réflexe de Matéo qui a détecté des bulles et procédé au changement de bloc. La descente à la purge lente est bien réalisée par Matéo, plus difficile pour Jérémie qui peine à rester au fond malgré ses efforts pour souffler. Les exercices de poumon ballast et REC sont réussis, mais Jérémie reste gêné par une stab trop petite et compense en palmant, ce qui affecte sa stabilisation. Les signes et la lecture du manomètre sont maîtrisés, et la gestion du matériel en fin de plongée est correcte. Jérémie progresse mais devra tester une stab adaptée et peut-être un léger lestage pour améliorer son confort et sa stabilité."
  },
  {
    "Moniteur": "Carine",
    "Date": "2025-10-28",
    "Eleve": "STEPHANE",
    "Role": "Encadrant",
    "CR": "Avec Stéphane, la séance s’est bien déroulée : gréage, dégréage, descente à la purge lente, stabilisation, signes, manomètre, REC et gestion du matériel en fin de plongée sont acquis. Il doit toutefois souffler davantage lors de la descente pour améliorer la compensation. Le gonflage du gilet en surface est correct, mais il cherche encore le bon bouton. Globalement, attitude sérieuse et progression régulière."
  },
  {
    "Moniteur": "Benoit L.",
    "Date": "2025-11-04",
    "Eleve": "TIMEO",
    "Role": "Encadrant",
    "CR": "Avec Timéo, l’exercice DBN a été réalisé sans stress et avec une grande facilité grâce à son expérience préalable en snorkeling. Il a assimilé le geste immédiatement et l’a confirmé par plusieurs répétitions, dont une traversée aller-retour du petit bassin en palmage avec expiration par le nez. Exercice validé et considéré comme acquis."
  },
  {
    "Moniteur": "Benoit P.",
    "Date": "2025-11-04",
    "Eleve": "ROBIN",
    "Role": "Encadrant",
    "CR": "Avec Robin, le saut droit est validé malgré quelques oublis du signe 👌 lors des mises à l’eau. La DBN a été réussie dès la première tentative, sans difficulté. Une initiation au vidage de masque (VDM) a été réalisée : Robin a compris le geste, mais le vidage complet reste compliqué avec le tuba. Aucun problème sur la nage avec palmes."
  },
  {
    "Moniteur": "Christophe",
    "Date": "2025-11-04",
    "Eleve": "STEPHANE",
    "Role": "Encadrant",
    "CR": "DBN dans le petit bain bien réalisé, avec ventilation dans le détendeur sans masque et expiration par le nez dans l’eau sans masque : OK.\nPassage en fosse : saut droit correct.\nAucune appréhension signalée, progression régulière sur les exercices.\nSéance courte mais efficace, bonne attitude générale."
  },
  {
    "Moniteur": "Véronique",
    "Date": "2025-11-04",
    "Eleve": "SACHA",
    "Role": "Encadrant",
    "CR": "Avec Sacha, le saut droit est impeccable et la DBN est maîtrisée dès la première tentative. Il a testé avec succès le vidage partiel du masque (VDM) et même le désembuage, sans crainte et avec enthousiasme. Bonne aisance générale et attitude positive tout au long de la séance. Il attend avec impatience le même programme que Jérémie dans 15 jours."
  },
  {
    "Moniteur": "Eddy",
    "Date": "2025-11-04",
    "Eleve": "JEREMIE",
    "Role": "Encadrant",
    "CR": "Avec Jérémie, le saut droit est très bien réalisé, complété par un bon palmage de sustentation dans la fosse. La DBN est maîtrisée et un VDM partiel a été effectué avec succès. En PMT dans le grand bassin, Jérémie montre un bon rythme et une excellente condition physique pour le palmage. Il est prêt pour la prochaine séance avec mise à l’eau en saut droit avec bloc et VDM partiel, voire total, si tout se passe bien."
  },
  {
    "Moniteur": "Carine",
    "Date": "2025-11-04",
    "Eleve": "MELINE",
    "Role": "Encadrant",
    "CR": "Méline a validé le saut droit dès la première tentative et a réalisé la DNB sans difficulté, parcourant même une longueur complète en palmage et tuba. La séance s’est déroulée agréablement, avec une bonne aisance aquatique et un comportement détendu. Elle s’est bien amusée, ce qui est encourageant pour la suite."
  },
  {
    "Moniteur": "Carlos",
    "Date": "2025-11-04",
    "Eleve": "JUDICAËL",
    "Role": "Encadrant",
    "CR": "Avec Jude, la séance a porté sur la DBN et le saut droit. Après plusieurs essais, il a réussi à vider son tuba et a compris le principe de la DBN, même si la pratique reste à consolider avant de tenter un vidage de masque au fond. Je lui ai montré le VDM pour lui expliquer son importance comme prérequis. Le saut droit est en cours d’acquisition : Jude a compris la théorie mais doit améliorer la posture pour éviter de sauter avec les jambes raides. Globalement, il progresse et assimile les conseils, mais nécessite encore des répétitions pour stabiliser ces compétences."
  },
  {
    "Moniteur": "Guillaume",
    "Date": "2025-11-04",
    "Eleve": "SAMY",
    "Role": "Encadrant",
    "CR": "Avec Samy et Florent, le saut droit est validé pour Florent dès la première tentative, tandis que Samy a eu besoin de quelques essais avant de réussir correctement. La DBN a été maîtrisée par les deux dès le premier essai, sans difficulté. Comme il restait du temps, une initiation au vidage de tuba a été réalisée, avec et sans soupape. Globalement, séance fluide et bien assimilée par les deux plongeurs."
  },
  {
    "Moniteur": "Guillaume",
    "Date": "2025-11-04",
    "Eleve": "FLORENT",
    "Role": "Encadrant",
    "CR": "Avec Samy et Florent, le saut droit est validé pour Florent dès la première tentative, tandis que Samy a eu besoin de quelques essais avant de réussir correctement. La DBN a été maîtrisée par les deux dès le premier essai, sans difficulté. Comme il restait du temps, une initiation au vidage de tuba a été réalisée, avec et sans soupape. Globalement, séance fluide et bien assimilée par les deux plongeurs."
  },
  {
    "Moniteur": "Benoit L.",
    "Date": "2025-11-18",
    "Eleve": "SACHA",
    "Role": "Encadrant",
    "CR": "Gréage un peu lent mais correctement réalisé ; difficulté à nommer les éléments de la stab → prévoir révision.\nSauts droits bien exécutés (PMT et équipé).\nDescente compliquée à cause de la compensation des oreilles, mais réussie après effort.\nCommunication sous l’eau maîtrisée, signes compris et exécutés sans stress.\nVDM bien perçu et réalisé sans erreur, mais un peu plus lent que Samy (3 réussites).\nBonne attitude globale, mais vigilance sur la dynamique compétitive avec Samy."
  },
  {
    "Moniteur": "Benoit L.",
    "Date": "2025-11-18",
    "Eleve": "SAMY",
    "Role": "Encadrant",
    "CR": "Gréage plus difficile au départ mais réussi en autonomie ; nomenclature encore fragile.\nSauts droits corrects (PMT et équipé).\nDescente rapide et bien maîtrisée (compensation efficace via Valsalva).\nCommunication sous l’eau fluide, signes connus et exécutés sans stress.\nVDM parfaitement intégré et exécuté rapidement, sans stress (3 réussites impeccables).\nTrès bonne maîtrise technique, mais tendance à la compétition avec Sacha à surveiller."
  },
  {
    "Moniteur": "Eddy",
    "Date": "2025-11-18",
    "Eleve": "GAËLLE",
    "Role": "Encadrant",
    "CR": "Après plusieurs semaines d’absence, elle a gréé son bloc avec quelques hésitations sur la boucle 02-13 mais globalement bien réalisé.\nDBN dans le petit bain très bien, aucune appréhension avec ou sans masque.\nEn fosse : deux sauts droits PMT corrects (le second mieux), bon palmage de sustentation après correction du mouvement.\nSaut droit avec bloc réussi sans peur, à confirmer la prochaine fois.\nDescente purge lente encore difficile mais en progrès ; elle a bien compris l’importance de souffler.\nVDM partiel : vidage de masque correct mais inclinaison de la tête à droite à corriger. Globalement, belle séance et elle était satisfaite."
  },
  {
    "Moniteur": "Carlos",
    "Date": "2025-11-18",
    "Eleve": "JUDICAËL",
    "Role": "Encadrant",
    "CR": "Gréage correct, mais manque encore de confiance pour dégréer seul ; capelage et décapelage bien réalisés.\nCommunication sous l’eau maîtrisée : signes classiques revus et compris (pression, monter, descendre, fin d’exercice, regarde-moi).\nDescente avec purge lente effectuée en autonomie mais difficulté à descendre et confusion entre les boutons de purge.\nPoumon ballast travaillé (assis, pompes, debout) avec bonne progression ; en mode « pompes » couché au fond, c’est OK.\nDéplacement entre deux eaux et DBN bien réalisés.\nVidage de masque partiel réussi ; vidage complet presque réussi (reste un peu d’eau mais à l’aise), pas besoin de remonter. REC et 360° corrects, signes OK au DP."
  },
  {
    "Moniteur": "Benoit P.",
    "Date": "2025-11-18",
    "Eleve": "FLORENT",
    "Role": "Encadrant",
    "CR": "Saut droit équipé OK pour Florent, \nInitiation à la purge rapide bien assimilée\nVDM en surface pour révisé et petite difficulté au début pour Stéphane qui avait oublié la DBN mais a bien réussi après remédiation.\nL'exercice du VDM total genou au fond a été validé\nLecture Mano OK, mais Florent ne m'a pas annoncé sa reserve avant que je ne lui demande.\nREC OK."
  },
  {
    "Moniteur": "Benoit P.",
    "Date": "2025-11-18",
    "Eleve": "STEPHANE",
    "Role": "Encadrant",
    "CR": "Pas évident pour Stéphane de gréer correctement son bloc.\nSaut droit équipé OK pour les 2, \nInitiation à la purge rapide bien assimilée par les 2\nVDM en surface pour révisé et petite difficulté au début pour Stéphane qui avait oublié la DBN mais a bien réussi après remédiation.\nL'exercice du VDM total genou au fond a été validé par les 2, même si j'ai senti par le regard Stéphane moins a l'aise.\nLecture Mano OK, mais Florent ne m'a pas annoncé sa reserve avant que je ne lui demande.\nREC OK pour les 2. même si Stéphane avait plus de mal a avoir une vitesse de remontée linéaire."
  },
  {
    "Moniteur": "Véronique",
    "Date": "2025-11-25",
    "Eleve": "ROBIN",
    "Role": "Encadrant",
    "CR": "Avec Robin, le gréage et la procédure restent à revoir : vocabulaire non acquis, oubli de la boucle 0213 et propositions incorrectes pour le branchement du DS. Le saut droit est validé avec une petite aide, mais la descente à la purge rapide manque de contrôle et Robin ne localise pas bien la purge une fois équipé. Le VDM est partiellement réussi : il ferme les yeux et n’a pas rempli complètement le masque, exercice à refaire. Communication, contrôle de consommation, poumon ballast et exercice “petit poucet” sont corrects, tout comme la REC, mais il a oublié le gonflage en surface. Globalement, Robin manque de concentration et d’organisation : il faudra limiter les objectifs, insister sur la mémorisation des procédures et renforcer l’attention."
  },
  {
    "Moniteur": "Benoit P.",
    "Date": "2025-11-25",
    "Eleve": "TIMEO",
    "Role": "Encadrant",
    "CR": "Avec Timéo, la séance s’est très bien déroulée : il est à l’aise avec le gréage et la communication. Son premier saut droit capelé a été bien réalisé malgré une appréhension initiale vite surmontée. La descente à la purge rapide est maîtrisée, et il a réussi trois VDM parfaitement dès la première série (masque peu immergé, puis complètement rempli). Les exercices ludiques avec lest et bouteille ont permis de consolider la théorie, et la REC avec rotation à 360° est validée. Seul point à améliorer : prendre l’initiative pour signaler la mi-pression et le froid."
  },
  {
    "Moniteur": "Hervé",
    "Date": "2025-11-25",
    "Eleve": "FLORENT",
    "Role": "Encadrant",
    "CR": "Avec Florent, la séance s’est déroulée sans problème : il a tout réalisé avec aisance et rapidité, en étant attentif et dynamique. Les exercices VDM complet, REC et purge sont validés sans difficulté. Seul point à noter : un souci de buée dans le masque, vu avec Eddy."
  },
  {
    "Moniteur": "Christophe",
    "Date": "2025-11-25",
    "Eleve": "JEREMIE",
    "Role": "Encadrant",
    "CR": "Avec Jérémie, le saut droit capelé est validé. Nous avons travaillé la gestion du lestage (0 à 8 kg) pour tester son confort et l’utilisation des purges et du DS : il faudra prévoir au moins 4 kg pour les prochaines séances. La stabilité et le poumon ballast ont été bien abordés, avec des parcours à profondeur définie et une bonne maîtrise des signes et du manomètre. Un vidage de masque partiel a été improvisé, mais le masque semble mal adapté à son visage, à vérifier lors de la prochaine séance. Jérémie est motivé, intelligent et très agréable à encadrer."
  },
  {
    "Moniteur": "Benoit L.",
    "Date": "2025-11-25",
    "Eleve": "MELINE",
    "Role": "Encadrant",
    "CR": "Avec Méline, la séance a été globalement difficile : le gréage reste non acquis, avec confusion sur les éléments et la boucle 0213 déjà faite avant l’exercice. Le saut droit équipé est presque correct, et la descente à la purge rapide a été réalisée sans problème de compensation. Elle a bien perçu le principe du poumon ballast et de la flottabilité lors des exercices, mais la séance a été écourtée à cause du froid (DBN et VDM non réalisés). Les signes de communication et la gestion de la consommation sont maîtrisés, ainsi que la remontée lente avec l’inflateur. Points à travailler : mémorisation des procédures, concentration et autonomie, avec un cours spécifique sur le gréage recommandé."
  },
  {
    "Moniteur": "Véronique",
    "Date": "2025-12-02",
    "Eleve": "TIMEO",
    "Role": "Encadrant",
    "CR": "Avec Timéo, la séance a été très satisfaisante : le canard PMT en fosse est validé après plusieurs essais, ainsi que le gréage et le saut droit. L’immersion en phoque avec purge rapide est réussie, et le VDM partiel puis presque complet est maîtrisé, même si Timéo hésite à refaire une deuxième manœuvre pour bien vider (à retenter en retirant le masque la prochaine fois). La balade équilibrée à 1,5 m du fond, le petit poucet et la REC avec arrêt au hublot sont bien réalisés. Il a terminé par un tour d’horizon et le gonflage de la stab en surface. Globalement, une séance très positive avec une bonne progression."
  },
  {
    "Moniteur": "Benoit L.",
    "Date": "2025-12-02",
    "Eleve": "SAMY",
    "Role": "Encadrant",
    "CR": "Avec Samy, la séance a été très positive : il sait défaire et refaire son sanglage en utilisant la boucle 0213, nomme correctement les éléments et réalise le gréage dans des temps corrects. Les mises à l’eau (saut droit PMT et équipé) sont validées, ainsi que la descente à la purge rapide, maîtrisée sans effet de chute. Les exercices de signes, poumon-ballast et stabilisation sont bien assimilés, malgré une tendance initiale à nager trop vite corrigée après rappel. Le travail avec poids et la remontée au DS sont réussis, avec une bonne compréhension des ajustements nécessaires. Globalement, Samy progresse rapidement, reste attentif et motivé, avec une attitude très favorable à la poursuite de la formation."
  },
  {
    "Moniteur": "Hervé",
    "Date": "2025-12-02",
    "Eleve": "SACHA",
    "Role": "Encadrant",
    "CR": "Avec Sacha, la séance s’est déroulée sans problème malgré son absence la semaine précédente. Il a réussi tous les exercices prévus sans hésitation et a découvert le petit poucet, qu’il a bien géré. Sacha est motivé, attentif et demandeur pour passer aux exercices suivants."
  },
  {
    "Moniteur": "Benoit P.",
    "Date": "2025-12-02",
    "Eleve": "JUDICAËL",
    "Role": "Encadrant",
    "CR": "Avec Judicaël, la séance a été mitigée : le gréage est en échec (boucle 0213 ratée, absence de vérification DS et purge) et la communication sur la consommation reste non acquise (mi-pression et réserve inconnues). Le saut droit PMT est réussi, mais le canard PMT a nécessité deux essais et la descente à la purge lente est correcte sans être fluide. Judicaël a réalisé une vingtaine de VDM réussis malgré un problème de masque, mais la stabilisation reste très difficile avec confusion entre inflateur et purge lente. La REC est validée mais manque de régularité, et la purge rapide a été travaillée en fin de séance avec succès. Globalement, Judicaël progresse lentement et nécessite un suivi pédagogique spécifique, avec des séances simplifiées pour limiter le nombre d’objectifs et renforcer la concentration."
  },
  {
    "Moniteur": "Benoit L.",
    "Date": "2025-12-09",
    "Eleve": "GAËLLE",
    "Role": "Encadrant",
    "CR": "Avec Gaëlle, la séance a été en demi-teinte : le gréage est correctement réalisé avec la boucle 0213 et le nommage des éléments acquis, mais la flottabilité a posé un gros problème qui a limité le travail au fond. Les mises à l’eau (saut droit PMT et équipé) sont validées, ainsi que la descente à la purge lente, malgré les difficultés de stabilisation. Les signes de communication et la gestion de la consommation sont bien compris, avec une réponse correcte sur la réserve. La remontée au DS et la REC sont maîtrisées, même si les derniers 50 cm sont un peu rapides. Pour la reprise, prévoir un essai avec un bloc 15 L pour améliorer la flottabilité ; Gaëlle reste motivée et attentive malgré ces difficultés."
  },
  {
    "Moniteur": "Véronique",
    "Date": "2025-12-09",
    "Eleve": "SACHA",
    "Role": "Encadrant",
    "CR": "Sacha a réalisé le gréage avec un peu de maladresse au niveau du mini bloc, nécessitant deux essais pour bien serrer, mais il a suivi la procédure sans oubli malgré un vocabulaire encore partiel. Le saut droit à la mise à l’eau était correct, sans être trop court. La descente en phoque a été difficile au départ à cause d’un bloc léger et d’un phoque timide, mais il a compris l’importance de bien souffler pour rester au fond. Les VDM ont été effectuées correctement et régulièrement pour enlever la buée du masque. Les signes étaient maîtrisés, même si la demande de conso a été ponctuelle, et l’équilibrage en balade comme à l’arrêt au hublot était bien réalisé. Enfin, les exercices PB, REC et le gonflage en surface ont été exécutés sans problème."
  },
  {
    "Moniteur": "Guillaume",
    "Date": "2025-12-09",
    "Eleve": "ROBIN",
    "Role": "Encadrant",
    "CR": "Robin est à l’aise dans l’eau et plonge avec facilité, mais son écoute des consignes reste limitée, ce qui complique l’apprentissage. Sa connaissance et utilisation du matériel sont fragiles : il comprend la logique mais oublie des points essentiels comme le 0213 et la plupart des vérifications, conséquence de son absentéisme. Le saut droit et la descente à la purge rapide sont bien maîtrisés, tandis que le phoque avec bloc demande encore du travail, même si le canard sans bloc est prometteur pour une première fois. Le vidage de masque reste perfectible : mauvaise remise du masque au premier essai et eau résiduelle au second, avec une tendance à ne pas remplir complètement le masque. La stabilisation est globalement bonne, malgré une surprise avec l’inflateur qui a nécessité une intervention, mais il sait se stabiliser en statique en jouant avec le poumon ballast. Enfin, la connaissance des signes est très faible, ce qui a été souligné au débrief avec insistance sur leur importance et sur la maîtrise du matériel."
  },
  {
    "Moniteur": "Benoit P.",
    "Date": "2025-12-09",
    "Eleve": "MELINE",
    "Role": "Encadrant",
    "CR": "Méline présente des difficultés avec le gréage et la dénomination du matériel, semblant assez perdue sur ces points. Les exercices techniques comme le saut droit, la descente à la purge rapide, le vidage de masque (qu’elle découvrait), le poumon ballast et le REC ont été réalisés correctement, sans difficulté majeure. La stabilisation est en cours d’acquisition mais ne pose pas de problème particulier. Le test du canard avec bloc (au lieu de sans bloc) a été raté sur le cassage, mais elle a bien protégé ses oreilles et compris la purge basse. Le dégréage est à revoir, car elle a oublié de fermer son bloc, heureusement presque vide. Enfin, le débrief n’a pas pu être fait sur place, mais a été transmis en message privé, avec un ressenti global d’approche « consommateur-touriste » similaire à celui évoqué par Benoit L."
  },
  {
    "Moniteur": "Carine",
    "Date": "2025-12-09",
    "Eleve": "TIMEO",
    "Role": "Encadrant",
    "CR": "Timeo et Florent ont bien réussi le canard, même si Timeo a dû répéter plusieurs fois pour corriger le cassage du bassin. Le gréage, dégréage, saut droit, immersion en phoque et descente à la purge rapide ont été correctement réalisés. Le vidage de masque posé au fond était globalement bon : Florent a eu besoin de plusieurs essais car il ne penchait pas assez la tête, tandis que Timeo a pris de l’assurance et a réussi un vidage complet. La stabilisation au hublot était correcte pour les deux. Aucun des deux n’a prévenu à mi-pression malgré un briefing insistant, ce qui montre qu’ils ne surveillent pas encore leur consommation. La remontée a été bien gérée avec une bonne vitesse et le gonflage du gilet en surface, ainsi qu’une gestion correcte du matériel à la sortie."
  },
  {
    "Moniteur": "Carine",
    "Date": "2025-12-09",
    "Eleve": "FLORENT",
    "Role": "Encadrant",
    "CR": "Timeo et Florent ont bien réussi le canard, même si Timeo a dû répéter plusieurs fois pour corriger le cassage du bassin. Le gréage, dégréage, saut droit, immersion en phoque et descente à la purge rapide ont été correctement réalisés. Le vidage de masque posé au fond était globalement bon : Florent a eu besoin de plusieurs essais car il ne penchait pas assez la tête, tandis que Timeo a pris de l’assurance et a réussi un vidage complet. La stabilisation au hublot était correcte pour les deux. Aucun des deux n’a prévenu à mi-pression malgré un briefing insistant, ce qui montre qu’ils ne surveillent pas encore leur consommation. La remontée a été bien gérée avec une bonne vitesse et le gonflage du gilet en surface, ainsi qu’une gestion correcte du matériel à la sortie."
  },
  {
    "Moniteur": "Hervé",
    "Date": "2025-12-09",
    "Eleve": "JEREMIE",
    "Role": "Encadrant",
    "CR": "Jérémy a validé les exercices PMT, phoque et apnée sans difficulté. En fosse, il a bien maîtrisé le gréage, le saut droit, le phoque et le canard avec bloc, ainsi que le vidage de masque complet avec stabilité. Les purges lente et rapide ont été correctement exécutées, tout comme l’exercice du « petit poucet ». Il faudra tester un ajout de lest (1 à 2 kg) ou un bloc de 15 L pour compenser sa corpulence. La gestion de la fin de plongée était très correcte, avec une bonne organisation et respect des procédures."
  },
  {
    "Moniteur": "Carlos",
    "Date": "2025-12-09",
    "Eleve": "SAMY",
    "Role": "Encadrant",
    "CR": "Samy a validé l’ensemble des exercices du programme de rentrée, ce qui montre une belle progression et un futur plongeur prometteur. Lors d’un échange de plombs en immersion, il a su réajuster sa flottabilité en utilisant les purges et le gonflage du gilet, avec une maîtrise presque parfaite. La séance s’est déroulée sans difficulté particulière et a confirmé sa bonne compréhension des bases techniques. Globalement, une très belle séance et un comportement attentif sous l’eau."
  },
  {
    "Moniteur": "Eddy",
    "Date": "2026-01-13",
    "Eleve": "STEPHANE",
    "Role": "Encadrant",
    "CR": "1/2 Séance dédiée Nage et PMT :\nles 100 m PMT et les 50 m capelé sont validés"
  },
  {
    "Moniteur": "Eddy",
    "Date": "2026-01-13",
    "Eleve": "JEREMIE",
    "Role": "Encadrant",
    "CR": "1/2 Séance dédiée Nage et PMT :\nles 100 m PMT et les 50 m capelé sont validés"
  },
  {
    "Moniteur": "Guillaume",
    "Date": "2026-01-13",
    "Eleve": "SACHA",
    "Role": "Encadrant",
    "CR": "J'etais avec Sacha et Samy.\nTout va bien pour eux, palmage très correct, 100m PMT et 50m capplé ok. \nLes apnée sont honorables et le tout en sécurité.\nIls sont appliqués et attentif, c'est aggréable d'etre avec eux."
  },
  {
    "Moniteur": "Guillaume",
    "Date": "2026-01-13",
    "Eleve": "SAMY",
    "Role": "Encadrant",
    "CR": "J'etais avec Sacha et Samy.\nTout va bien pour eux, palmage très correct, 100m PMT et 50m capplé ok. \nLes apnée sont honorables et le tout en sécurité.\nIls sont appliqués et attentif, c'est aggréable d'etre avec eux."
  },
  {
    "Moniteur": "Benoit P.",
    "Date": "2026-01-27",
    "Eleve": "JEREMIE",
    "Role": "Encadrant",
    "CR": "dans le 25m, révision du vidage de masque total au fond bien réalisé. on a refait l'exercice en stabilisation c'était pas evident dans 2m de fond de ne pas toucher la surface ou le fond mais au bout du 3eme essai Jeremie a réussi (c'est un peu son talon d'Achille la stabilisation). LRE des 2 façons OK alors on a fait des pannes d'air dans les 2 sens : il a bien géré meme s'il s'est fait surprendre en faisant fusé un peu fort l'octopus dans la bouche. remediation et réussite. on a fini par faire une longueur en assistance panne d'air."
  },
  {
    "Moniteur": "Véronique",
    "Date": "2026-01-27",
    "Eleve": "ROBIN",
    "Role": "Encadrant",
    "CR": "Bonjour, pour Robin\nLRE sur expiration et inspiration ok\nPanne d'air avec Octopus receveur et donneur ok\nOn a fait panne d'air avec échange d'embout simulé ok.\nTout cela en statique. \nVidage de masque, il le fait spontanément. \nDonne sa conso.\nJe l'ai un peu sollicité pour répondre à la question ok, mais ok. \nÉquilibrage. Se débrouille bien surtout s'il y fait bien attention sur consigne. Sinon se laisse un peu porter.\nGréage à l'envers, il a commencé par le détendeur. Pas encore très automatique.\nBien à l'aise malgré tout et plus d'écoute et de respect des consignes."
  },
  {
    "Moniteur": "Eddy",
    "Date": "2026-01-27",
    "Eleve": "JUDICAËL",
    "Role": "Encadrant",
    "CR": "-  LRE sur inspiration et sur expiration OK\n- Panne d'air sur octopus donneur et receveur en statique puis dynamique OK\nEntre temps j'ai fait de l'équilibrage et du vdm. Il a toujours un souci d'équilibrage, tendance à remonter et il gère très mal la purge lente tout comme la purge rapide. A revoir.  Il a enlevé son masque complètement puis vidage complet, c'était bien. Cependant il n'incline pas assez la tête en arrière pour un vidage rapide et efficace."
  },
  {
    "Moniteur": "Benoit L.",
    "Date": "2026-01-27",
    "Eleve": "STEPHANE",
    "Role": "Encadrant",
    "CR": "Contrôle de l'ensemble du matériel en mode lui sachant et moi apprenant :\nL'ensemble complet \"bloc + détendeur + stab\" est parfaitement connu et expliquer \nLe garage est maîtrise y compris la boucle qui a été démontée et remontée complètement et du premier coup \nRévision des signes RAS\nGeste technique présenté ce soir LRE, et à sa demande du vidange de masque complet \nLa LRE  en expiration et inspiration sont maîtrisées. Pour les prochains moniteur sur lre Stéphane prend son temps, on le voit prendre la maîtrise du geste qu'il refait dans sa tête, puis il s'exécute doucement mais c'est un geste clair et posé \nBref l'asuis est quasiment là.\n\nLe seul signe en fin de plongée qu'il ne semblait pas connaître c'est le signe du froid."
  },
  {
    "Moniteur": "Benoit P.",
    "Date": "2026-02-03",
    "Eleve": "SAMY",
    "Role": "Encadrant",
    "CR": "VDM à genoux au fond + stabilisation à mi-profondeur : très bien exécutés\nLRE inspiration / expiration : très à l’aise pour une première expérience\nRéaction à panne d’air statique (mon exercice) : très bonne\nPanne d’air personnelle : exécutée avec calme et aisance\nPanne d’air dynamique : très bien réalisée\nPanne d’air “surprise” avec diversion (flashlight) : excellente réactivité, pas piégé\nVDM sans masque (retrait complet) : aucun stress, maîtrise totale (prise de temps pour nettoyer le masque avant remise)"
  },
  {
    "Moniteur": "Guillaume",
    "Date": "2026-02-03",
    "Eleve": "JUDICAËL",
    "Role": "Encadrant",
    "CR": "Le gréage et le matériel c'est encore assez faible, j'ai dû lui montrer de quel côté monter le détendeur. \nLe vidage de masque a été compliqué, nous avons dû remonter une 1ere fois en surface pour le vider. Puis un partiel bien fait suivit d'un blocage sur un complet ou il soufflait par la bouche. (J'ai fini part vider son masque moi même avec l'air de mon détendeur). Mais au final je valide avec un dernier essai réussi après remédiation.\nLa panne d'air et le lâché/reprise est bien réalisée. Il faut continuer a le travailler pour bien ancré le geste.\nLa stabilisation ça va mieux mais il y a encore un peu de boulot."
  },
  {
    "Moniteur": "Carine",
    "Date": "2026-02-10",
    "Eleve": "JUDICAËL",
    "Role": "Encadrant",
    "CR": "- greage / degreage : encore un peu hésitant mais bien dans l’ensemble\n- saut droit sans bloc : bien, merite un pas un peu plus grand\n- canard : ok\n- immersion : ok\n- vdm : s’y prend à plusieurs reprises car à tendance à souffler par la bouche et non le nez\n- lre sur inspi : ok\n- panne d’air sur octopus : ok. Réagit bien\n- échange d’embout : ok\n- stabilisation (palier) : à travailler. N’arrive pas à doser le gonflage et dégonflage. Une fois à la bonne profondeur, je lui ai fait lâcher son DS et il s’est stabilisé.\n-rec et 360 : ok"
  },
  {
    "Moniteur": "Benoit L.",
    "Date": "2026-02-10",
    "Eleve": "FLORENT",
    "Role": "Encadrant",
    "CR": "Gréage avec annonce complet des équipements et des phases dans le bon ordre et sans aucun soucis\nSais et reconnais l'ensemble des éléments. \nL'ensemble des exercices du programme annoncés ont été tous réalisés :\nSaut droit/canard sans, puis avec équipement == OK\nEnsemble des scénarios perçu et réagis correctement sans stress.\nVDM, LRE parfaitement compris et réalisé à la demande\nVidage de masque partiel et complet sans soucis\nConso/froid désormais parfaitement intégré et répondu à la demande du moniteur\nPanne d'air reçu/donné avec déplacement == OK\n\nSeul petit point à améliorer :\nutilise encore un peu trop ses mains/bras dès lors que l'on est en mouvement.\nla position n'est pas encore super allongée"
  },
  {
    "Moniteur": "Eddy",
    "Date": "2026-02-10",
    "Eleve": "ROBIN",
    "Role": "Encadrant",
    "CR": "Il a toujours du mal à rester concentré quelques minutes....Il faut donc lui donner un brief court au départ puis lorsque les ateliers ont été vus, en refaire un autre pour la suite. Ceci implique un retour surface...\n- Gréage : il monte toujours son gilet à l'envers sur le bloc! Comme le joint de son bloc était mort, il a dû en reprendre un autre. Cela lui a fait du bien de gréer 2 fois 😂\n- Canard en PMT : pas mal dans l'ensemble\n- Canard avec bloc : pas mal aussi\n- LRE sur expiration et inspiration : Ok\n- Panne d'air sur octopus donneur : ok en statique et en cours d'acquisition en dynamique car se placer du mauvais côté et oubli de tenir le plongeur en déplacement\n- Panne d'air sur octopus receveur : Ok en statique et en dynamique.\n- Palier à 2m : il le tient sans trop bouger\n\nPour résumer, il est très à l'aise dans l'eau, sait bien s'équilibrer et assure une bonne cohésion de palanquée en restant près du moniteur."
  },
  {
    "Moniteur": "Benoit P.",
    "Date": "2026-02-10",
    "Eleve": "SACHA",
    "Role": "Encadrant",
    "CR": "Canard PMT il a tendance a plier les genoux au moment de lancer les jambes. Il protège bien ses oreilles.\nGréage 👌🏻 \nCanard a travaillé, il a tendance a prendre la bouteille dans la tête (petit gabarit) sûrement dû au manque d'inclinaison du haut du corp en amont. Donc ca le perturbe a garder la purge basse en main.\nVDM 👌🏻 \nLRE 👌🏻(inspi et expi) \nPanne d'air 👌🏻 (assistant et assisté/ statique et dynamique)\nEchange d'embout simulé 👌🏻...mais hésitant.\nRemonté 360° 👌🏻 \nCommunication : mélange un peu mi-pression et reserve.\n\nConclusion : va falloir trouvé du ludique pour pas qu'il ne s'ennuie sur la fin de l'année.\nA travaillé : le canard et ... la sortie des locaux a 23h00."
  },
  {
    "Moniteur": "Véronique",
    "Date": "2026-02-10",
    "Eleve": "SAMY",
    "Role": "Encadrant",
    "CR": "canard PMT OK\ncanard avec bloc: encore un peu de travail, il ne vide pas assez la stab, commence le vidage avec purge basse à l'horizontale (commencer à vider en surface avec purge haute), fait plusieurs fois avec progrès.\nVDM: pas de sujet, il le fait spontanément quand nécessaire\nLRE: 2 cas ok\nDonner, recevoir de l'air OCTOPUS: ok en statique mais lâche son détendeur, en équilibrage ok mais pas en déplacement non encore expliqué\nEchange d'embout en statique: ok"
  },
  {
    "Moniteur": "Carlos",
    "Date": "2026-02-10",
    "Eleve": "JEREMIE",
    "Role": "Encadrant",
    "CR": "Il a acheté un nouveau gillet (Stab).\nIl a voulu la tester. Mais comme il n'avait pas dit qu'il plongeait avec des plombs avec les autres stabs. Gréage très bien jusqu'a la mise à l'eau. Immersion en canard il bien compris, mais il était perdu avec les nouvelles purges... Il avait assez bien fait de canard en plongée libre... Impossible de se poser au fond tout seul... demande de réalisation de plusieurs exercices c'était très compliqué, car il avait beaucoup de mal a se stabilisé, il remontait quasiment en surface, il était complément perdu avec la nouvelle stab. Nous avons conclu que pour la prochaine séance il serait impératif d'avoir minimum 2 kilos dans la stab  à voir 4 kilos. \nIl a bien réagi à ma panne d'air, et il a bien signalé sa panne d'air. Séance très chaotique... Nous avons conclu ensemble de répéter la séance avec la nouvelle stab, mais sans oublier les plombs..."
  },
  {
    "Moniteur": "Benoit L.",
    "Date": "2026-02-17",
    "Eleve": "TIMEO",
    "Role": "Encadrant",
    "CR": "Ce soir grosse, de rattrapage (suite à ses quelques absences) avec réalisation complète du programme, et même sur les points non vus. (il lui manquait la panne d'air : le signe et la procédure d'aide)\n\nJ'ai donc passé en revu :\n\nMatériel + gréage le tout correctement annoncé et monté (y compris la boucle 0213 refaite de A-Z) en moins de 5 minutes\n\nSaut droit + canard en PMT = OK\n\nPetite appréhension sur canard en profondeur jusqu'à venir me faire un check à 4m 50, mais au 2ème essai c'est franchement ok\n\nMême exercice équipé : une démo immergé pour lui rappeler que la main doit être sur la purge basse dès la surface avant la bascule vers l'avant : Au 1er test ==> ok réussi:\n\nPas vraiment de palmage en surface car la purge a été trouvée directement et il a pensé à vider ses poumons en phase descente\n\nVidage de masque Ok : genou posé et équilibré (pas vraiment de signe de stress, et le geste est posé et clairement fait)\nRéponse juste à l'ensemble des signes annoncé\n\nUne 1ère pour lui ce soir : le signe panne d'air\n(on a vite fait un debrief au sec avant pour expliquer / rappeler la LRE, geste qui amène à la panne d'aire)\n\nLRE expiration/inspiration ok : pas de stress et réalisé à la demande.\nTour de cuve en mode panne d'air reçu/donné == ok\nExo équilibrage et déplacement pour vérifier que le poumon balast est réalisé correctement : la variation est vraiment légère \nSur la fin REC et remonté controlé sur purge == ok \ntour horizon dans la zone des 2 m puis stop == la stabilisation était pas mal\nPuis remontée en surface avec geste Ok"
  },
  {
    "Moniteur": "Guillaume",
    "Date": "2026-02-17",
    "Eleve": "SAMY",
    "Role": "Encadrant",
    "CR": "Aucun souci avec lui. Très à l'aise, il s'équipe rapidement et sans aide, connais son matériel, s'équilibre très bien, et connais tous les signes.\n\nCanard sans bloc : ok\nCanard avec bloc: a purgé un peu trop tard donc plus difficile mais ok.\nLRE inspiration et expiration : ok\nVDM : ok\nPanne d'air : donne et reçois de l'air sur octopus et échange simulé, en statique et en dynamique. (Oubli juste parfois d'attraper le binôme lorsqu'il donne de l'air)\nÉquilibrage : ok on est même passé à des exercices un peu plus durs en statique.\nREC : ok avec palier et 360."
  },
  {
    "Moniteur": "Benoit P.",
    "Date": "2026-02-17",
    "Eleve": "ROBIN",
    "Role": "Encadrant",
    "CR": "Gros soucis au niveau du gréage (fixe son étrier sur la sortie DIN, place les éléments totalement a l'envers), il ne sait pas nommer le manomètre et se trompe sur la lecture de celui ci.\nQuand je lui dit qu'il y a un soucis, il n'arrive pas a voir le problème au niveau de son gréage.\nJe lui ai dit de prendre un bloc de taille normal pour s'entraîner en situation.\nTrès dispersé, difficile d'obtenir son attention.\n\n2 canards en PMT ok\n2 canards en bloc ne vide pas assez sa purge avant et pendant l'immersion.\nVDM ok\nLRE (inspi et expi): fait fuser trop fort en remise en bouche.\nRéaction panne d'air : trop long a réagir, a chercher a me donner son détendeur au lieu de son octopus, ne m'a pas attraper.\nRemontée à vitesse  bien maîtrisée en 360°\n\nCécilia (DP) m'a fait remarqué, a juste titre, que le temps de plongée avait été trop court car la mise a l'eau était trop tardive.\n\nEn conclusion : Robin a une bonne aisance aquatique mais est très (trop) dilettant."
  },
  {
    "Moniteur": "Eddy",
    "Date": "2026-02-17",
    "Eleve": "JEREMIE",
    "Role": "Encadrant",
    "CR": "Je lui ai proposé de prendre un bloc de 12L court (plus lourd qu'un 12L long). Je n'ai pas trouvé de bloc 15L et heureusement car en lui faisant le test du lestage en surface, il ne s'est même pas arrêté avec de l'eau à mi-masque car il est descendu directement en purgeant son gilet. \nIl descend bien en canard sans bloc mais ce n'est pas le cas avec bloc : en cours d'acquisition.\nPar la suite on a fait :\n- LRE : ok\n- vdm complet : ok\n- descente en phoque : ok\n- Panne d'air sur octopus en dynamique : ne pense pas à me tenir sinon réaction rapide. Par contre il n'a pas mis l'attache octopus laissée sur l'ancien gilet. Vérifiez la prochaine fois qu'il l'a bien ré-installée sur sa nouvelle stab. Je rappelle à tous, ne pas mettre l'octopus dans la poche du gilet, normalement ils ont tous une attache ou un nez de clown. Je leur en ai donné un ou une en octobre.\n- Déplacement équilibré : ok sauf lorsqu'on lui demande sa consommation, il se déconcentre et remonte. La preuve qu'il ne souffle pas assez régulièrement et a tendance à garder trop d'air dans ses poumons. Compte tenu de sa capacité pulmonaire, il remonte fatalement.\n- Tenue de palier : ça bouge un peu mais c'est pas mal\n- REC : on a fait notre remontée en 30 secondes avec un 360° et il a pu voir que c'est long !\n\nConclusion on va lui laisser prendre pendant quelques semaines un bloc de 12L court puis par la suite il prendra un 12L long et je pense qu'en lui faisant le test du lestage il aura de l'eau mi-masque en purgeant tout. On vérifiera ce"
  },
  {
    "Moniteur": "Véronique",
    "Date": "2026-02-17",
    "Eleve": "SACHA",
    "Role": "Encadrant",
    "CR": "Gréage, dégréage ok, je suis arrivée un peu après donc il ne m'a pas nommé les différents éléments mais c'était pas mal il y a 15 jours.\nMise à l'eau en saut droit ok, il avait envie pour s'entraîner.\nCanard: il en a fait 2, le 1er impeccable, pour le 2ème il a dû s'y reprendre à 2 fois, il avait échappé sa purge basse, mais ok au 2ème essai.\nPanne d'air en statique ok - Panne d'air en déplacement ok, il avait oublié de me tenir, la 1ère fois mais ensuite ok. Je lui ai montré que celui qui était en panne d'air pouvait aussi tenir l'autre.\nEchange d'embout ok, posé au fond et équilibré à 50 cm du fond. \nVDM OK, spontanément pour enlever la buée de son masque.\nSignes ok - REC et 360 ok\ngonflage un peu timide à la surface.\nPlus à l'aise sur l'équilibrage.\nTrès content. Il se sent bien et a vraiment la sensation de progresser."
  },
  {
    "Moniteur": "Virginie",
    "Date": "2026-02-17",
    "Eleve": "STEPHANE",
    "Role": "Encadrant",
    "CR": "Greage : ok très méthodique mais un peu long.\nCanard plongée libre : ok\nÉquipage dans l'eau et canard avec bouteille : bien pour une 1ere fois ECA\nLRE : Ok \nPanne d'air : ECA de manière générale idem 1ere fois. Nous avons vu donner/recevoir de l'air en statique et donner de l'air en déplacement\nVDM : mi masque ok\nTour horizon et vitesse remontée : ECA"
  },
  {
    "Moniteur": "Carlos",
    "Date": "2026-02-17",
    "Eleve": "STEPHANE",
    "Role": "Encadrant",
    "CR": "Greage : ok très méthodique mais un peu long.\nCanard plongée libre : ok\nÉquipage dans l'eau et canard avec bouteille : bien pour une 1ere fois ECA\nLRE : Ok \nPanne d'air : ECA de manière générale idem 1ere fois. Nous avons vu donner/recevoir de l'air en statique et donner de l'air en déplacement\nVDM : mi masque ok\nTour horizon et vitesse remontée : ECA"
  },
  {
    "Moniteur": "Benoit L.",
    "Date": "2026-02-24",
    "Eleve": "JEREMIE",
    "Role": "Encadrant",
    "CR": "Gros atelier ce soir avec un passage en revue de quasiment toutes les compétences\nSaut droit équipé OK, Lamage surface puis canard équipé OK\nSignes et LRE/DBN/VDM validé\nSeul signe pas testé ce soir c'était essoufflement car j'ai oublié\n\nPuis passage en activité équilibrée :\nSignes/ communication OK\nReste en point a continuer : stabilisation maintenu plus de 2 minutes\nDès qu'un évènement vient le perturber, il a tendance à reprendre une ventilation importante et cela vient perturber son équilibrage,\nPalmage entre 2 eaux avec séquence de signes aléatoires = toutes les réponses sont bonnes et quasi immédiates\nEnfin la REC avec un palier pui 360 et signe en surface ==> OK pour moi\nGréage/Dégréage complet désormais bien autonome ==> Ok pour moi"
  },
  {
    "Moniteur": "Benoit P.",
    "Date": "2026-02-24",
    "Eleve": "STEPHANE",
    "Role": "Encadrant",
    "CR": "Preparation, gréage, capelage et communication 👌🏻 \n\nCanard avec bloc, il a du mal a purger sa stab en descendant, donc il ne descent pas.\n\nVdm 👌🏻  (mais pas en stabilisé car prend trop d'air)\n\nLRE 👌🏻 \n\nPanne d'air sur moniteur: trop lent a réagir.\nPanne d'air sur élève: j'ai été obligé de lui coller l'octopus dans la bouche car il faisait une apnée  et ne prenais pas l'octopus (j'ai été un peu surpris 😲) en plus avec l'apnée il remontais 🫁🤕\n\nA du mal a se stabiliser en règle générale, il ne souffle pas assez."
  },
  {
    "Moniteur": "Christophe",
    "Date": "2026-02-24",
    "Eleve": "TIMEO",
    "Role": "Encadrant",
    "CR": "Gréage OK\nMise à l’eau en saut droit OK \nCanard à améliorer, ne purge pas assez, mauvaise position du corps et des jambes. \nVidage de masque complet Ok  (sans stabilisation) \nSignes OK \nLRE (en inspi et expi) OK \nAssistance panne d’air donner son octobre OK puis déplacement horizontal \nEtre assisté en panne d’air OK \nGestion du gilet et poumon ballast OK \nMise en sécu en surface, gonflage du gilet Ok\nPassage du bloc sur bord du bassin et degréage OK \n\nDe manière générale il est très à l’aise dans l’eau, il communique bien (m’a indiqué les 100 Bars)  je lui avait demandé de me prévenir. \nUtilise très bien le poumon ballast et n’évolue presque qu’avec cela."
  },
  {
    "Moniteur": "Virginie",
    "Date": "2026-02-24",
    "Eleve": "FLORENT",
    "Role": "Encadrant",
    "CR": "Greage : ok \nCanard plongée libre : ok\nÉquipage dans l'eau : ok\nCanard avec bouteille : quasi ok,  à peaufiner pour la purge arrière.\nLRE : Ok \nPanne d'air (statique et déplacement) : ok\nVDM : ok\nÉchange embout simulé : ECA bien pour une 1ere fois mais lui rappeler que c'est environ 2 cycles respiratoires avant l'échange (il avait tendance à faire qu'1 cycle donc à ne pas assez respirer)\nRec, tour horizon et vitesse remontée : ok\nDegreage : ok\nDe manière générale très à l'aise, je n'ai pas vu de difficultés particulières."
  },
  {
    "Moniteur": "Benoit L.",
    "Date": "2026-03-03",
    "Eleve": "STEPHANE",
    "Role": "Encadrant",
    "CR": "Bonsoir à tous,\n\n1ère partie TIV (2 bloc a refaire avec Pascal), donc pas suivi la partie entrainement PMT\n\n2ème partie avec Stéphane (bassin 25M puisque la fosse non accessible ce soir)\nMise à l'eau avec équipement en surface\nBalayage complet signe ==> Ok\n\nSuivi de conso OK (plusieurs fois tout au long de l'immersion)\n\nSait  reconnaître les cas et sait les annoncer de Réserve / mi pression\n\nVDM/LRE/Panne d'air = ensemble correctement compris et perçus : pas de pb à la réalisation\n\nLe seul point a continuer d'améliorer c'est la partie stabilisation.\nParfois bien pendant 3 minutes puis un exo ou un changement de cap dans le bassin lui fait perdre sa rigueur et hop trop de poumon ballast et a tendance à remonter\n\nSinon pour la remonté c'est acquis = pas trop vite, 360 et signe fait == Ok"
  },
  {
    "Moniteur": "Benoit P.",
    "Date": "2026-03-03",
    "Eleve": "JEREMIE",
    "Role": "Encadrant",
    "CR": "Nage en immersion.\nCommunication.\nVDM, LRE, assistance et assisté sur octopus, simulation échange d'embout. \nTout est globalement bien effectué.\nOn a essayé de travailler la stabilisation qui est son point faible. \nIl prend encore des gros volumes en inspiration. Il a du mal a se mettre a genou au fond, on sent que ca lui demande une concentration pour descendre.\nLes exercices en stabilisation sont compliqué."
  },
  {
    "Moniteur": "Benoit L.",
    "Date": "2026-03-10",
    "Eleve": "ROBIN",
    "Role": "Encadrant",
    "CR": "Robin ce soir était fatigué et pas là. Breifing compliqué à garder son attention du début à la fin.\nLe capelage complet mais lent et peu argumenté à l'oral, ne savait plus comment se nome le type de détenteur (étrier ou DIN, première tentative octopus et DS mis à droite mais il sait corrigé de lui même avant que je n'intervienne...)\nSi la mise à l'eau en saut droit était bonne, le préparatif a été long, mais long ...\nSéance rapide mais l'ensemble des points sont à l'attendue.\nLa partie échange simulée n'a été faite qu'au sec et laborieuse, donc noté en orange"
  },
  {
    "Moniteur": "Eddy",
    "Date": "2026-03-10",
    "Eleve": "JUDICAËL",
    "Role": "Encadrant",
    "CR": "- gréage ok\n- il a un peu oublié l'immersion en phoque donc un petit rappel bien utile\n- vdm complet à genou avec son nouveau masque : ne souffle pas ou peu par le nez donc vide difficilement son masque, à revoir\n- panne d'air octopus statique : ok\n- panne d'air octopus en déplacement : encore un manque de réactivité mais les gestes sont acquis\n- équilibrage au fond : OK\nBalade en slalomant entre les plongeurs :  dès qu'il se déconcentre, il a tendance à remonter voir être à la limite de percer. De plus, il se trompe facilement sur les boutons de la purge lente, donc cela n'aide pas 😂.\nSinon je trouve qu'il a bien progressé et qu'il lui faut plus de temps que la moyenne pour assimiler les différentes compétences. Il est dans la bonne voie pour être prêt pour le Frioul."
  },
  {
    "Moniteur": "Véronique",
    "Date": "2026-03-10",
    "Eleve": "SAMY",
    "Role": "Encadrant",
    "CR": "gréage ok, serrage de la boucle un peu maladroite (maintenir la stab et tirer sur la boucle en même temps)\nsaut droit ok\nimmersion phoque ok\nVDM OK, il le fait souvent, son masque a l'air un peu petit, il prend l'eau et la buée\nLRE OK\npanne d'air sur octopus en déplacement ok\npanne d'air avec échange d'embout posé au fond ok\nEquilibrage au fond ok\nBalade : ok, est capable de corriger sa profondeur\nREC ok, \ntour d'horizon ok"
  },
  {
    "Moniteur": "Virginie",
    "Date": "2026-03-10",
    "Eleve": "JEREMIE",
    "Role": "Encadrant",
    "CR": "J'ai plongé avec Jérémie qui avait  un bloc 15L (tableau rempli)\nGreage : ok\nSaut droit : ok\nDescente phoque : ok\nLre : ok\nPanne d'air statique et déplacement : ok\nVDM : il a eu besoin pour vider son masque de s'y reprendre en plusieurs fois mais il a bien géré ok\nÉquilibrage et déplacement : ok\nDéplacement à mi profondeur / hublot : ok\nRemontée et 360 : ok\nOn a refait du poumon ballast etc, il maîtrise de mieux en mieux sa ventilation et avec bloc 15l il arrivait bien s'équilibrer"
  },
  {
    "Moniteur": "Carlos",
    "Date": "2026-03-10",
    "Eleve": "SACHA",
    "Role": "Encadrant",
    "CR": "Gréage : ok\nSaut droit : ok\nDescente phoque : ok\nLre : en inspiratoire ou expiratoire - ok\nPanne d'air statique et déplacement : ok\nVDM : Parfait, il enlever son masque pour les frotter et la remis et vidé d'un seul coup.\nÉquilibrage et déplacement : ok avec quelques geste s parasite\nDéplacement à mi profondeur / hublot : ok\nRemontée et 360 : ok\nNous avons vu l'essouflement. Il a bien compris comment le démontrer (faire le geste), et les risque aux quels peut-il entrainer. Comment agir toute en avertissant son guide de palanquée. Sur lui-même ou sur un camarade.\nBelle séance..."
  },
  {
    "Moniteur": "Carlos",
    "Date": "2026-03-17",
    "Eleve": "JEREMIE",
    "Role": "Encadrant",
    "CR": "En accord avec l'ensemble des moniteurs présents ce soir, j'ai validé la bascule arrière en PMT et en scaphandre pour nos 6 adhérents présents."
  },
  {
    "Moniteur": "Catherine",
    "Date": "2026-03-17",
    "Eleve": "JUDICAËL",
    "Role": "Encadrant",
    "CR": "En accord avec l'ensemble des moniteurs présents ce soir, j'ai validé la bascule arrière en PMT et en scaphandre pour nos 6 adhérents présents."
  },
  {
    "Moniteur": "Benoit P.",
    "Date": "2026-03-17",
    "Eleve": "SACHA",
    "Role": "Encadrant",
    "CR": "En accord avec l'ensemble des moniteurs présents ce soir, j'ai validé la bascule arrière en PMT et en scaphandre pour nos 6 adhérents présents."
  },
  {
    "Moniteur": "Eddy",
    "Date": "2026-03-17",
    "Eleve": "SAMY",
    "Role": "Encadrant",
    "CR": "En accord avec l'ensemble des moniteurs présents ce soir, j'ai validé la bascule arrière en PMT et en scaphandre pour nos 6 adhérents présents."
  },
  {
    "Moniteur": "Virginie",
    "Date": "2026-03-17",
    "Eleve": "STEPHANE",
    "Role": "Encadrant",
    "CR": "En accord avec l'ensemble des moniteurs présents ce soir, j'ai validé la bascule arrière en PMT et en scaphandre pour nos 6 adhérents présents."
  },
  {
    "Moniteur": "Véronique",
    "Date": "2026-03-17",
    "Eleve": "TIMEO",
    "Role": "Encadrant",
    "CR": "En accord avec l'ensemble des moniteurs présents ce soir, j'ai validé la bascule arrière en PMT et en scaphandre pour nos 6 adhérents présents."
  },
  {
    "Moniteur": "Benoit L.",
    "Date": "2026-03-24",
    "Eleve": "JUDICAËL",
    "Role": "Encadrant",
    "CR": "Montage/gréage ok\n\nSaut droit ok mais en revanche le canard n'est pas maîtrisé, il doit être revu rapidement\n\nVDM, LRE, Panne d'air et leur signe sont connus et reconnus\n\nMaitrise sans panic le fait de chercher et proposer son octopus au moniteur\n\nEn balade, il y a trop de mouvement de bras , main pied qui l'empêche de se maintenir et de se stabiliser.\nSur essoufflement il a perçu la procédure de son encadrant et a joué le jeu\n\nEnfin de programme, je lui ai imposer de prendre un position verticale, de se tenir les mains devant lui pour que je puisse lui montrer la notion d'action --> attente de l'inertie --> puis seulement nouvelle action. nous avons donc pu faire une remontée cool, lente et tenir 1 bonne minute à 1m50 de la surface."
  },
  {
    "Moniteur": "Benoit P.",
    "Date": "2026-03-24",
    "Eleve": "SACHA",
    "Role": "Encadrant",
    "CR": "Gréage et saut droit ok\n\nAvais oublié le signe essoufflement pendant me briefing au sec.\n\nCanard  il a du mal a purger totalement sa stab. Mais a bien équilibré ses oreilles.\n\nLRE, Panne d'air (dans les 2 sens en dynamique), échange simulé : ok\n\nEssoufflement avec la planquée Virginie & Samy : ok\n\nRemonté a vitesse contrôlée avec palier de 30 secondes et 360 parfait.\n\nPendant le debriefing surface on a un peu papoter théorie (pression) et sur ce point ca pêche un peu plus par rapport a la pratique."
  },
  {
    "Moniteur": "Carine",
    "Date": "2026-03-24",
    "Eleve": "JEREMIE",
    "Role": "Encadrant",
    "CR": "Avec Jeremy, tout était ok. Il a bien progressé. Petit bémol sur le maintien d’un palier qui reste encore fragile."
  },
  {
    "Moniteur": "Christophe",
    "Date": "2026-03-24",
    "Eleve": "ROBIN",
    "Role": "Encadrant",
    "CR": "La présentation du matériel faite avec une nonchalance assez déconcertante, un manque d'intérêt visible. C'est dommage parce que ça donne le ton !! \nLe gréage en lui-même était correct, bon montage des éléments, rien à redire là-dessus. Bravo \n\nBriefing fait avant la mise à l'eau, saut droit bien exécuté, pas de souci.\n\nÇa s'est compliqué au moment du départ en phoque. Pas maîtrisé du tout et avec problème de purge non géré, il s'est retrouvé à se débattre en surface pendant plusieurs secondes. Pas idéal… \nSous l'eau, les choses se sont un peu arrangées avec descente, lâché-reprise d'embout correct, la gestion de la panne d'air s'est bien passée dans les deux sens (donner et recevoir l'octopus), échange d'embout OK. Ces exercices-là, il les a assurés c’est positif.\n\nEn revanche, gros point noir sur la stabilisation. Vraiment pas à l'aise avec la gestion du poumon-ballast et ça s'est vu tout au long de la plongée. J'ai dû reprendre le sujet avec lui pendant la séance et ne pas faire les exercices sur l’essoufflement.  La remontée aussi était problématique  trop rapide et impossible de se stabiliser (jusqu’a percer en surface) et en surface il n'a pas encore le réflexe de gonfler sa stab.\n\nPoint important à noter (DANGER)  il fait la valsalva à la remontée. Je lui ai bien expliqué les risques et remis ça dans le contexte du cours sur les barotraumatismes auquel il avait assisté pourtant. \nA surveiller, d'autant qu'il semble avoir des oreilles assez sensibles.\n\nIl doit vraiment travailler l'utilisation de l'inflateur et des purges rapides. Le dégréage s'est bien passé.\n\nBref, les bases techniques commencent à s'installer et certaines choses sont très bien mais Robin doit s'engager un peu plus et surtout se concentrer un minimum."
  },
  {
    "Moniteur": "Virginie",
    "Date": "2026-03-24",
    "Eleve": "SAMY",
    "Role": "Encadrant",
    "CR": "Plongée avec Samy tableau remplit, à l'écoute, suis les consignes et exos ok. Oublié de revoir le canard à prévoir mardi."
  },
  {
    "Moniteur": "Carlos",
    "Date": "2026-03-24",
    "Eleve": "STEPHANE",
    "Role": "Encadrant",
    "CR": "Nous avons vu tous les critères prévus de la séance. Toute est validé, il reste encore des améliorations à faire sur la stabilité, il fait encore quelques gestes parasites, mais reste une très belle séance."
  },
  {
    "Moniteur": "Benoit P.",
    "Date": "2026-03-31",
    "Eleve": "JEREMIE",
    "Role": "Encadrant",
    "CR": "Avec Véronique évaluation théorique de Jeremie.\n\nDans l'ensemble Jeremie a les connaissances, pas toujours facile de mener la trame de l'évaluation. Quelques oublis de sa part (nombre de personnes dans une palanquée, les niveaux d'encadrement, le signe \"ca va pas\").\nOn a ete un peu (trop) long a l'interroger, donc pas de mise a l'eau pour lui en 2nde partie.\nOn a refait un gréage (avec Ben. L) et Jeremie a pu présenter son direct system atypique."
  },
  {
    "Moniteur": "Véronique",
    "Date": "2026-03-31",
    "Eleve": "JEREMIE",
    "Role": "Encadrant",
    "CR": "Bonsoir à tous, comme a indiqué Benoît, pour la théorie de Jérémie, je valide. Quelques oublis indiqués par Benoît, par contre il a travaillé les connaissances physiques, peut-être un peu trop. Parfois ça embrouille. Un peu stressé aussi. Pour moi, c'est ok"
  },
  {
    "Moniteur": "Benoit L.",
    "Date": "2026-03-31",
    "Eleve": "STEPHANE",
    "Role": "Encadrant",
    "CR": "Avec Virginie évaluation théorie de Stéphane\n\nL'ensemble du parcours théorie a été vu et clairement su / exprimé \nNous validons cet examen Théorique"
  },
  {
    "Moniteur": "Virginie",
    "Date": "2026-03-31",
    "Eleve": "STEPHANE",
    "Role": "Encadrant",
    "CR": "Avec Virginie évaluation théorie de Stéphane\n\nL'ensemble du parcours théorie a été vu et clairement su / exprimé \nNous validons cet examen Théorique"
  },
  {
    "Moniteur": "Eddy",
    "Date": "2026-03-31",
    "Eleve": "SAMY",
    "Role": "Encadrant",
    "CR": "hier j'avais Samy et Judicaël.\n- Canard PMT : ok pour les deux\n- Canard avec bloc : ils l'ont fait deux fois et le geste n'est pas encore académique (d'ailleurs on ne demande pas cela pour un N1) mais validable car ils ont bien purgé leur gilet et sont descendus au fond sans palmer. \n- LRE : ok\n- Panne d'air sans les prévenir : ils ont bien géré en me donnant leur octopus et le déplacement était fluide\n- Équilibrage et tenue du palier : Ok pour Samy mais il y a encore du travail pour Jude ! il fait le yoyo fréquemment et parfois perce ! En plus je pense qu'il se trompe souvent de bouton sur son direct system.\n- REC : Ok\nPour résumer, Samy peut passer l'examen pratique dès mardi prochain et on va attendre un peu pour Jude en travaillant essentiellement la gestion des purges et l'équilibrage."
  },
  {
    "Moniteur": "Eddy",
    "Date": "2026-03-31",
    "Eleve": "JUDICAËL",
    "Role": "Encadrant",
    "CR": "hier j'avais Samy et Judicaël.\n- Canard PMT : ok pour les deux\n- Canard avec bloc : ils l'ont fait deux fois et le geste n'est pas encore académique (d'ailleurs on ne demande pas cela pour un N1) mais validable car ils ont bien purgé leur gilet et sont descendus au fond sans palmer. \n- LRE : ok\n- Panne d'air sans les prévenir : ils ont bien géré en me donnant leur octopus et le déplacement était fluide\n- Équilibrage et tenue du palier : Ok pour Samy mais il y a encore du travail pour Jude ! il fait le yoyo fréquemment et parfois perce ! En plus je pense qu'il se trompe souvent de bouton sur son direct system.\n- REC : Ok\nPour résumer, Samy peut passer l'examen pratique dès mardi prochain et on va attendre un peu pour Jude en travaillant essentiellement la gestion des purges et l'équilibrage."
  },
  {
    "Moniteur": "Carlos",
    "Date": "2026-03-31",
    "Eleve": "TIMEO",
    "Role": "Encadrant",
    "CR": "’ai plongé avec Timéo et Robin tous les deux avec une bonne aisance aquatique !! \nMais très attentions aux plusieurs dissipations de Robin. Conseil en plongée avec Robin être très vigilant, car il peut remonter vite en surface s’il pense avoir des soucis …Je lui fait la morale, car il me la fait mardi dernier pendant que j’observais Timéo et nous avons bien discuté de l’accident de surpression Pulmonaire. Il serait judicieux de plonger seul avec lui en fosse à Ville Neuve…\nGréage OK\nSaut droit OK\nSigne demandés Ok\nCanard bien fait mais à refaire prochainement pour les deux.\nLRE OK \nPanne d’air OK \nDonner et recevoir OK \nPanne d’air sur un seul embout OK \nÉvolution stabilisée OK \nRemontée contrôlée, 360, sortie lente à la surface avec signe OK."
  },
  {
    "Moniteur": "Carlos",
    "Date": "2026-03-31",
    "Eleve": "ROBIN",
    "Role": "Encadrant",
    "CR": "’ai plongé avec Timéo et Robin tous les deux avec une bonne aisance aquatique !! \nMais très attentions aux plusieurs dissipations de Robin. Conseil en plongée avec Robin être très vigilant, car il peut remonter vite en surface s’il pense avoir des soucis …Je lui fait la morale, car il me la fait mardi dernier pendant que j’observais Timéo et nous avons bien discuté de l’accident de surpression Pulmonaire. Il serait judicieux de plonger seul avec lui en fosse à Ville Neuve…\nGréage OK\nSaut droit OK\nSigne demandés Ok\nCanard bien fait mais à refaire prochainement pour les deux.\nLRE OK \nPanne d’air OK \nDonner et recevoir OK \nPanne d’air sur un seul embout OK \nÉvolution stabilisée OK \nRemontée contrôlée, 360, sortie lente à la surface avec signe OK."
  },
  {
    "Moniteur": "Christophe",
    "Date": "2026-03-31",
    "Eleve": "SACHA",
    "Role": "Encadrant",
    "CR": "J’ai plongé avec Sacha qui est au top !! \n\nGréage OK\nSaut droit OK\nCanard (2 fois) bien fait \nLRE OK \nPanne d’air OK \nDonner et recevoir OK \nPanne d’air sur un seul embout OK \nÉvolution stabilisée OK \nRemontée lente , 360, palier d’1 min , sortie lente à la surface avec signe OK \n\nNota : Ne connaissait pas le signe froid sous l’eau, peut être lui refaire les différents signes en révision mardi."
  },
  {
    "Moniteur": "Benoit P.",
    "Date": "2026-04-07",
    "Eleve": "TIMEO",
    "Role": "Encadrant",
    "CR": "En 1ere partie EVALUATION THEORIQUE avec TIMEO (qui est venu pour cette évaluation exclusivement car malade) \nPas grand chose a reprendre sur cette évaluation car Timéo a déroulé en 30min ce qui lui a été demandé. Un petit peu plus hésitant sur la bio.\nJe valide son évaluation"
  },
  {
    "Moniteur": "Eddy",
    "Date": "2026-04-07",
    "Eleve": "SAMY",
    "Role": "Encadrant",
    "CR": "- validation de la pratique pour Samy, Sacha et Jérémie (qui a très bien progressé). Ils sont prêts pour la fosse du 19 avril.\n\nOn peut être fier d'eux et aussi de nous pour leur avoir donné toutes les billes pour atteindre les compétences demandées.\n\nJ'aurais plaisir à les encadrer en mer pour profiter pleinement de l'environnement tout en sachant qu'ils savent se stabiliser, faire un palier et répondre à mes différentes demandes."
  },
  {
    "Moniteur": "Eddy",
    "Date": "2026-04-07",
    "Eleve": "SACHA",
    "Role": "Encadrant",
    "CR": "- validation de la pratique pour Samy, Sacha et Jérémie (qui a très bien progressé). Ils sont prêts pour la fosse du 19 avril.\n\nOn peut être fier d'eux et aussi de nous pour leur avoir donné toutes les billes pour atteindre les compétences demandées.\n\nJ'aurais plaisir à les encadrer en mer pour profiter pleinement de l'environnement tout en sachant qu'ils savent se stabiliser, faire un palier et répondre à mes différentes demandes."
  },
  {
    "Moniteur": "Eddy",
    "Date": "2026-04-07",
    "Eleve": "JEREMIE",
    "Role": "Encadrant",
    "CR": "- validation de la pratique pour Samy, Sacha et Jérémie (qui a très bien progressé). Ils sont prêts pour la fosse du 19 avril.\n\nOn peut être fier d'eux et aussi de nous pour leur avoir donné toutes les billes pour atteindre les compétences demandées.\n\nJ'aurais plaisir à les encadrer en mer pour profiter pleinement de l'environnement tout en sachant qu'ils savent se stabiliser, faire un palier et répondre à mes différentes demandes."
  },
  {
    "Moniteur": "Benoit L.",
    "Date": "2026-04-07",
    "Eleve": "SACHA",
    "Role": "Encadrant",
    "CR": "- Exo Saut droit, palmage de surface avant Canard pour immersion à 4,5 M pour rejoindre Carlos\n\n           ==> Ok pour Sacha, Samy\n\n        - Plusieurs exos enchainés sur demande aléatoire des moniteurs \n\n           ==> Conso, VDM, LRE, Signe du froid, Panne d'air proche puis panne d'air distante (4/5M max) de l'élève pour apnée et palmage pour venir chercher de l'air auprès du moniteur, Palmage sur Panne d'air en binôme bien maitrisée par Sacha, Samy et Jérémie qui nous avait rejoind"
  },
  {
    "Moniteur": "Benoit L.",
    "Date": "2026-04-07",
    "Eleve": "SAMY",
    "Role": "Encadrant",
    "CR": "- Exo Saut droit, palmage de surface avant Canard pour immersion à 4,5 M pour rejoindre Carlos\n\n           ==> Ok pour Sacha, Samy\n\n        - Plusieurs exos enchainés sur demande aléatoire des moniteurs \n\n           ==> Conso, VDM, LRE, Signe du froid, Panne d'air proche puis panne d'air distante (4/5M max) de l'élève pour apnée et palmage pour venir chercher de l'air auprès du moniteur, Palmage sur Panne d'air en binôme bien maitrisée par Sacha, Samy et Jérémie qui nous avait rejoind"
  },
  {
    "Moniteur": "Benoit L.",
    "Date": "2026-04-07",
    "Eleve": "JEREMIE",
    "Role": "Encadrant",
    "CR": "- Exo Saut droit, palmage de surface avant Canard pour immersion à 4,5 M pour rejoindre Carlos\n\n           ==> Ok pour Sacha, Samy\n\n        - Plusieurs exos enchainés sur demande aléatoire des moniteurs \n\n           ==> Conso, VDM, LRE, Signe du froid, Panne d'air proche puis panne d'air distante (4/5M max) de l'élève pour apnée et palmage pour venir chercher de l'air auprès du moniteur, Palmage sur Panne d'air en binôme bien maitrisée par Sacha, Samy et Jérémie qui nous avait rejoind"
  },
  {
    "Moniteur": "Virginie",
    "Date": "2026-04-14",
    "Eleve": "JUDICAËL",
    "Role": "Encadrant",
    "CR": "Greage ok\nSaut droit : n'a pas attendu mon ok pour mise à l'eau à bien vérifier la prochaine fois. Carlos était en check surface car Judicael ne semblait pas encore à l'aise sur le saut droit. Sinon petit saut au lieu d'un grand pas mais sinon le geste tech était ok. Donc ECA général pour le saut droit.\nCanard : 1ère fois Ko, a recommencé ECA, je l'ai arrêté en cours car il n'equilibrait pas ses oreilles.\nLRE : OK\nPanne d'air : Ok\nÉchange embout : En 2x. 1ere fois brouillon/précipité, 2eme fois ok\nÉquilibrage sous l'eau : ECA de mieux en mieux, on a refait un peu de poumon ballast\nVDM : ECA on l'a fait plusieurs fois car il ne mettait pas vraiment d'eau dans le masque, puis Ok la dernière fois. Démarre le geste la tête trop en arrière je trouve, je lui ai dit. \nPalier : ECA il a tendance à un peu descendre ou remonter.\nDe manière générale il se précipite un peu pour les exos mais quand je l'ai arrêté et lui ai montré de le faire tranquillement c'était beaucoup mieux, encore qq séances et ça devrait être ok pour la pratique N1."
  },
  {
    "Moniteur": "Benoit P.",
    "Date": "2026-04-14",
    "Eleve": "FLORENT",
    "Role": "Encadrant",
    "CR": "En 2nde partie: palanquée Florent avec Véronique Ben&Ben\nBascule arrière validé en PMT et en bloc.\nFlorent n'avait pas vu le signe et le cours sur l'essoufflement. On lui a montré comment se placer. \nOn a vu comment se placer en déplacement de palanquée.\nPanne d'air a distance.\nRemontée avec palier de 3min.\nDans tout ces exercices Flo était en aisance aquatique.\nIl a, comme demandé en briefing, annoncé ses 130bars.\nLes absences a plusieurs cours pour Florent font qu'il n'a pas toutes les connaissances mais ca va vite se rattraper."
  },
  {
    "Moniteur": "Véronique",
    "Date": "2026-04-14",
    "Eleve": "FLORENT",
    "Role": "Encadrant",
    "CR": "Même constat pour moi. \nBalade sous l'eau avec différents gestes techniques: à refaire la semaine prochaine en plus construit. Globalement Florent est à l'aise sous l'eau et avec les gestes de base."
  },
  {
    "Moniteur": "Eddy",
    "Date": "2026-04-14",
    "Eleve": "STEPHANE",
    "Role": "Encadrant",
    "CR": "Je viens de valider le N1 pour Stéphane et Timéo. Le tableau est rempli pour tous les deux concernant la réussite de l'examen pratique. Très bien pour les 2 excepté un tout petit détail, lors de la panne d'air pour eux il oublie de garder en main leur détendeur principal. Ils n'oublieront plus maintenant, du moins je l'espère...\nJe vous enverrai dimanche soir une trame pour les 2 prochaines semaines ainsi qu'un petit debrief sur la fosse du matin."
  },
  {
    "Moniteur": "Eddy",
    "Date": "2026-04-14",
    "Eleve": "TIMEO",
    "Role": "Encadrant",
    "CR": "Je viens de valider le N1 pour Stéphane et Timéo. Le tableau est rempli pour tous les deux concernant la réussite de l'examen pratique. Très bien pour les 2 excepté un tout petit détail, lors de la panne d'air pour eux il oublie de garder en main leur détendeur principal. Ils n'oublieront plus maintenant, du moins je l'espère...\nJe vous enverrai dimanche soir une trame pour les 2 prochaines semaines ainsi qu'un petit debrief sur la fosse du matin."
  },
  {
    "Moniteur": "Benoit L.",
    "Date": "2026-04-14",
    "Eleve": "FLORENT",
    "Role": "Encadrant",
    "CR": "Mardi 2ème partie avec Florent : \nInitiation bascule arrière pour rattraper la séance précédente.\nEn atelier, tout d'abord en PMT avec un premier test réussi et validé par Benoit et moi même.\nOn a tenté une bascule équipée dans la foulée et Florent a bien su gérer le geste et le matériel.\nBilan : avec Benoit on valide aussi ce geste équipé."
  },
  {
    "Moniteur": "Fred C. (E2 Grp2)",
    "Date": "2026-04-19",
    "Eleve": "ROBIN",
    "Role": "Encadrant",
    "CR": "Fred : Robin\nAu programme, découverte des 20 mètres, LRE et VDM, signes, contrôles purges et communication \nGréage un peu lent notamment avec la sangle de bloc \nDescente très lente, sinus entravés...\nPour tout le reste, c'était très bien..! Bon comportement, écoute ok, conso ok, il était content...\nD'une manière générale, de ce que j'ai vu, les candidats sont bons..!!\nBravo à toute l'équipe de cadres du G1 pour le boulot accompli 👏🏻✨"
  },
  {
    "Moniteur": "Olivier H. (E2 Grp2)",
    "Date": "2026-04-19",
    "Eleve": "JEREMIE",
    "Role": "Encadrant",
    "CR": "Olivier : Jérémie\nBelle séance, Jérémie est vraiment à l'aise \nBonne communication, positionnement durant toute la plongée en respect des consignes demandées durant mon brief\nRéponse aux signes bien\nLRE VDM posé 5m puis 20m ras\nEn stabilisé légère montée sur le LRE mais <1m\nRéaction panne d'air top\nBonne gestion de la vitesse et maintien d'un palier \nDu potentiel pour un bon plongeur"
  },
  {
    "Moniteur": "Eddy",
    "Date": "2026-04-19",
    "Eleve": "FLORENT",
    "Role": "Encadrant",
    "CR": "Eddy : Judicaël et Florent *\nOn a fait le même programme cité par Fred à 6m puis à 20m. Descente lente pour Jude dans le 20m en se tenant à l’échelle. Il flippait ! Mais tout s’est bien passé et ne s’est même pas rendu compte que l’on était au fond. Au fond tout était ok pour les exercices. Remontée lente avec bonne cohésion de la palanquée et maintien du palier à 5m. Petit passage dans le 10m. RAS. Florent est très à l’aise et va vite rattraper son retard. Jude a bien progressé et a bien géré sa stab. Bravo à lui. Bref belle séance avec 2 plongeurs sympas et qui vont bien kiffer la sortie Frioul\nVictor : Timéo"
  },
  {
    "Moniteur": "Eddy",
    "Date": "2026-04-19",
    "Eleve": "JUDICAËL",
    "Role": "Encadrant",
    "CR": "Eddy : Judicaël et Florent *\nOn a fait le même programme cité par Fred à 6m puis à 20m. Descente lente pour Jude dans le 20m en se tenant à l’échelle. Il flippait ! Mais tout s’est bien passé et ne s’est même pas rendu compte que l’on était au fond. Au fond tout était ok pour les exercices. Remontée lente avec bonne cohésion de la palanquée et maintien du palier à 5m. Petit passage dans le 10m. RAS. Florent est très à l’aise et va vite rattraper son retard. Jude a bien progressé et a bien géré sa stab. Bravo à lui. Bref belle séance avec 2 plongeurs sympas et qui vont bien kiffer la sortie Frioul\nVictor : Timéo"
  },
  {
    "Moniteur": "Victor P. (E2 Grp2)",
    "Date": "2026-04-19",
    "Eleve": "TIMEO",
    "Role": "Encadrant",
    "CR": "Victor : Timéo \n\nHello Eddy. On a plongé 30min . Fin de plongée à 90bars pour Timeo. RAS sur les exos. Bonnes réactions aux signes panne d'air/ consommation. LRE VDM ok. Bonne stabilité même à la remontée. Il ne s'est pas laissé emporter vers la surface. Bonne gestion de la stab et du  PB. J'ai aperçu qu'il avait froid à la fin (tremblement ) mais il dit que ça va. C'est peut être le point de vigilance a avoir pour les sorties mer. C'était une très belle première plongée à 20m. Bien formé !"
  },
  {
    "Moniteur": "Véronique",
    "Date": "2026-04-21",
    "Eleve": "ROBIN",
    "Role": "Encadrant",
    "CR": "Première partie, examen de théorie avec Robin, veuillez excuser Benoît qui était enrhubé! Mais qui a tout dit. Robin s'est débrouillé comme un chef, je ne l'ai pas reconnu !"
  },
  {
    "Moniteur": "Virginie",
    "Date": "2026-04-21",
    "Eleve": "FLORENT",
    "Role": "Encadrant",
    "CR": "En 2ème partie évaluation théorique de Florent accompagné de Virginie.\nIl a déroulé tout a la perfection.\nLes seuls erreurs sont sur les baro, il avait oublié le masque et le systeme digestif, mais quand on les a abordé, il a su parfaitement nous dire les résolutions/préventions. \n\nOn peut dire que Florent est un bon plongeur. Qu'il est a l'aise dans l'eau comme en théorie."
  },
  {
    "Moniteur": "Benoit P.",
    "Date": "2026-04-21",
    "Eleve": "FLORENT",
    "Role": "Encadrant",
    "CR": "En 2ème partie évaluation théorique de Florent accompagné de Virginie.\nIl a déroulé tout a la perfection.\nLes seuls erreurs sont sur les baro, il avait oublié le masque et le systeme digestif, mais quand on les a abordé, il a su parfaitement nous dire les résolutions/préventions. \n\nOn peut dire que Florent est un bon plongeur. Qu'il est a l'aise dans l'eau comme en théorie."
  },
  {
    "Moniteur": "Véronique",
    "Date": "2026-04-21",
    "Eleve": "JUDICAËL",
    "Role": "Encadrant",
    "CR": "Deuxième jeu d'équilibrage avec plombs comme l'a expliqué Benoît. \nJudicaël n'est pas encore au top. Il n'arrête pas de gonfler, dégonfler et fait du yoyo sans arrêt. Il faudrait lui enlever 😂. \nDonc pas d'expérimentation avec les poids. \nStéphane a réussi à compenser. C'est ok."
  },
  {
    "Moniteur": "Véronique",
    "Date": "2026-04-21",
    "Eleve": "STEPHANE",
    "Role": "Encadrant",
    "CR": "Deuxième jeu d'équilibrage avec plombs comme l'a expliqué Benoît. \nJudicaël n'est pas encore au top. Il n'arrête pas de gonfler, dégonfler et fait du yoyo sans arrêt. Il faudrait lui enlever 😂. \nDonc pas d'expérimentation avec les poids. \nStéphane a réussi à compenser. C'est ok."
  }
]